[
    {
        "File": "D:\\ghast\\downloads\\CLANNAD\\KOE\\0001\\Z000101002.ogg",
        "Text": "聞こえないのか、ともやっ",
        "Name": "担任"
    },
    {
        "File": "D:\\ghast\\downloads\\CLANNAD\\KOE\\0001\\Z000101003.ogg",
        "Text": "春原はどこだ？",
        "Name": "担任"
    },
    {
        "File": "D:\\ghast\\downloads\\CLANNAD\\KOE\\0001\\Z000101004.ogg",
        "Text": "探して連れてきてくれないか",
        "Name": "担任"
    },
    {
        "File": "D:\\ghast\\downloads\\CLANNAD\\KOE\\0001\\Z000101005.ogg",
        "Text": "そう、おまえだ、ともや",
        "Name": "担任"
    },
    {
        "File": "D:\\ghast\\downloads\\CLANNAD\\KOE\\0001\\Z000101006.ogg",
        "Text": "おまえなら見当がつくんじゃないのかと思ってだよ",
        "Name": "担任"
    },
    {
        "File": "D:\\ghast\\downloads\\CLANNAD\\KOE\\0001\\Z000101007.ogg",
        "Text": "そうかぁ…",
        "Name": "担任"
    },
    {
        "File": "D:\\ghast\\downloads\\CLANNAD\\KOE\\0001\\Z000101008.ogg",
        "Text": "なら、おまえを代わりに呼ぶことになるぞ",
        "Name": "担任"
    },
    {
        "File": "D:\\ghast\\downloads\\CLANNAD\\KOE\\0001\\Z000101009.ogg",
        "Text": "もちろん、職員室だよ",
        "Name": "担任"
    },
    {
        "File": "D:\\ghast\\downloads\\CLANNAD\\KOE\\0001\\Z000101010.ogg",
        "Text": "ともや、おまえは、自分の遅刻の数を知っているのか？",
        "Name": "担任"
    },
    {
        "File": "D:\\ghast\\downloads\\CLANNAD\\KOE\\0001\\Z000101011.ogg",
        "Text": "そういうのを五十歩百歩というんだぞ",
        "Name": "担任"
    },
    {
        "File": "D:\\ghast\\downloads\\CLANNAD\\KOE\\0001\\Z000101012.ogg",
        "Text": "とにかく、春原がいないんだったら、順番としてはおまえになるんだよ",
        "Name": "担任"
    },
    {
        "File": "D:\\ghast\\downloads\\CLANNAD\\KOE\\0001\\Z000101013.ogg",
        "Text": "おい、ともやっ、今からじゃないぞっ、授業が終わってからだぞっ！",
        "Name": "担任"
    },
    {
        "File": "D:\\ghast\\downloads\\CLANNAD\\KOE\\0001\\Z000101084.ogg",
        "Text": "おい、春原っ",
        "Name": "担任"
    },
    {
        "File": "D:\\ghast\\downloads\\CLANNAD\\KOE\\0001\\Z000101085.ogg",
        "Text": "今日こそは、職員室まで連行だっ",
        "Name": "担任"
    },
    {
        "File": "D:\\ghast\\downloads\\CLANNAD\\KOE\\0001\\Z000101091.ogg",
        "Text": "捕まえたぞっ",
        "Name": "担任"
    },
    {
        "File": "D:\\ghast\\downloads\\CLANNAD\\KOE\\0001\\Z000101093.ogg",
        "Text": "おまえら、ほんと、仲がいいな。なんなら、ふたり一緒に…",
        "Name": "担任"
    },
    {
        "File": "D:\\ghast\\downloads\\CLANNAD\\KOE\\0015\\Z001515505.ogg",
        "Text": "…以上が、連絡事項だ",
        "Name": "担任"
    },
    {
        "File": "D:\\ghast\\downloads\\CLANNAD\\KOE\\0015\\Z001515506.ogg",
        "Text": "３時になったら一旦教室に戻ってくること",
        "Name": "担任"
    },
    {
        "File": "D:\\ghast\\downloads\\CLANNAD\\KOE\\0015\\Z001515507.ogg",
        "Text": "それまでは各自自由。今日一日は受験のことを忘れて羽根をのばしなさい",
        "Name": "担任"
    },
    {
        "File": "D:\\ghast\\downloads\\CLANNAD\\KOE\\0023\\Z002323942.ogg",
        "Text": "なんだ、おまえたち、職員室に用か？",
        "Name": "担任"
    },
    {
        "File": "D:\\ghast\\downloads\\CLANNAD\\KOE\\0023\\Z002323944.ogg",
        "Text": "誰が、象印だっ、乾（いぬい）だっ",
        "Name": "担任"
    },
    {
        "File": "D:\\ghast\\downloads\\CLANNAD\\KOE\\0023\\Z002323945.ogg",
        "Text": "で、なんなんだ。どうせロクな…",
        "Name": "担任"
    },
    {
        "File": "D:\\ghast\\downloads\\CLANNAD\\KOE\\0023\\Z002323946.ogg",
        "Text": "っと…珍しいな。女の子連れか",
        "Name": "担任"
    },
    {
        "File": "D:\\ghast\\downloads\\CLANNAD\\KOE\\0023\\Z002323947.ogg",
        "Text": "君、こいつらに騙されてないか。大丈夫か？",
        "Name": "担任"
    },
    {
        "File": "D:\\ghast\\downloads\\CLANNAD\\KOE\\0023\\Z002323950.ogg",
        "Text": "ん？  どういうことだい",
        "Name": "担任"
    },
    {
        "File": "D:\\ghast\\downloads\\CLANNAD\\KOE\\0023\\Z002323951.ogg",
        "Text": "そうか、そりゃ、難儀だな…",
        "Name": "担任"
    },
    {
        "File": "D:\\ghast\\downloads\\CLANNAD\\KOE\\0023\\Z002323952.ogg",
        "Text": "部として認めてもらうには、まずは顧問をつけること、これが第一条件だ",
        "Name": "担任"
    },
    {
        "File": "D:\\ghast\\downloads\\CLANNAD\\KOE\\0023\\Z002323955.ogg",
        "Text": "それだけじゃ駄目なんだな",
        "Name": "担任"
    },
    {
        "File": "D:\\ghast\\downloads\\CLANNAD\\KOE\\0023\\Z002323957.ogg",
        "Text": "乾だっ！",
        "Name": "担任"
    },
    {
        "File": "D:\\ghast\\downloads\\CLANNAD\\KOE\\0023\\Z002323958.ogg",
        "Text": "しかも、おまえ、今、教師の名前を呼び捨てにしたな？",
        "Name": "担任"
    },
    {
        "File": "D:\\ghast\\downloads\\CLANNAD\\KOE\\0023\\Z002323960.ogg",
        "Text": "どうだかな…",
        "Name": "担任"
    },
    {
        "File": "D:\\ghast\\downloads\\CLANNAD\\KOE\\0023\\Z002323962.ogg",
        "Text": "ああ、もうひとつ条件がある",
        "Name": "担任"
    },
    {
        "File": "D:\\ghast\\downloads\\CLANNAD\\KOE\\0023\\Z002323963.ogg",
        "Text": "入部希望者が３名以上居ること",
        "Name": "担任"
    },
    {
        "File": "D:\\ghast\\downloads\\CLANNAD\\KOE\\0023\\Z002323964.ogg",
        "Text": "ま、その点に関しては大丈夫みたいだな",
        "Name": "担任"
    },
    {
        "File": "D:\\ghast\\downloads\\CLANNAD\\KOE\\0023\\Z002323966.ogg",
        "Text": "まだ、時間あるから、今から、演劇部の元顧問、探してみるかい？",
        "Name": "担任"
    },
    {
        "File": "D:\\ghast\\downloads\\CLANNAD\\KOE\\0023\\Z002323967.ogg",
        "Text": "訊けば、すぐ見つかると思うよ",
        "Name": "担任"
    },
    {
        "File": "D:\\ghast\\downloads\\CLANNAD\\KOE\\0023\\Z002323969.ogg",
        "Text": "どうした？",
        "Name": "担任"
    },
    {
        "File": "D:\\ghast\\downloads\\CLANNAD\\KOE\\0023\\Z002323972.ogg",
        "Text": "え？  足らないの？",
        "Name": "担任"
    },
    {
        "File": "D:\\ghast\\downloads\\CLANNAD\\KOE\\0023\\Z002323973.ogg",
        "Text": "そっか…こいつらが、演劇をやるわけないか…",
        "Name": "担任"
    },
    {
        "File": "D:\\ghast\\downloads\\CLANNAD\\KOE\\0023\\Z002323974.ogg",
        "Text": "それだと難しいな",
        "Name": "担任"
    },
    {
        "File": "D:\\ghast\\downloads\\CLANNAD\\KOE\\0023\\Z002323975.ogg",
        "Text": "そもそも演劇部は、部員が集まらなくなって、廃部になったんだからね",
        "Name": "担任"
    },
    {
        "File": "D:\\ghast\\downloads\\CLANNAD\\KOE\\0023\\Z002323977.ogg",
        "Text": "おっと、そろそろ戻らないと",
        "Name": "担任"
    },
    {
        "File": "D:\\ghast\\downloads\\CLANNAD\\KOE\\0023\\Z002323978.ogg",
        "Text": "悪いね。また、相談事があったら、言っておいで",
        "Name": "担任"
    },
    {
        "File": "D:\\ghast\\downloads\\CLANNAD\\KOE\\0027\\Z002727496.ogg",
        "Text": "おい、ともや",
        "Name": "担任"
    },
    {
        "File": "D:\\ghast\\downloads\\CLANNAD\\KOE\\0027\\Z002727497.ogg",
        "Text": "なぁ、ともや。今日、おまえの家にいくぞ",
        "Name": "担任"
    },
    {
        "File": "D:\\ghast\\downloads\\CLANNAD\\KOE\\0027\\Z002727498.ogg",
        "Text": "おまえだけ、進路相談が終わっていない",
        "Name": "担任"
    },
    {
        "File": "D:\\ghast\\downloads\\CLANNAD\\KOE\\0027\\Z002727499.ogg",
        "Text": "いいわけあるか。進学しないにしても、必要だ",
        "Name": "担任"
    },
    {
        "File": "D:\\ghast\\downloads\\CLANNAD\\KOE\\0027\\Z002727500.ogg",
        "Text": "おまえん家、あれだろ。親父さんだけだろ？",
        "Name": "担任"
    },
    {
        "File": "D:\\ghast\\downloads\\CLANNAD\\KOE\\0027\\Z002727501.ogg",
        "Text": "どうして、連絡つかないんだ？  いるんだろ？",
        "Name": "担任"
    },
    {
        "File": "D:\\ghast\\downloads\\CLANNAD\\KOE\\0027\\Z002727502.ogg",
        "Text": "いないわけないだろ。なんだ、ずっと帰っていないのか",
        "Name": "担任"
    },
    {
        "File": "D:\\ghast\\downloads\\CLANNAD\\KOE\\0027\\Z002727503.ogg",
        "Text": "じゃあ、確かめに行ってやるから、ここで待ってろ。支度してくるからな",
        "Name": "担任"
    },
    {
        "File": "D:\\ghast\\downloads\\CLANNAD\\KOE\\0027\\Z002727549.ogg",
        "Text": "なんだ、ともや、女の子なんて連れて",
        "Name": "担任"
    },
    {
        "File": "D:\\ghast\\downloads\\CLANNAD\\KOE\\0027\\Z002727550.ogg",
        "Text": "なにっ？",
        "Name": "担任"
    },
    {
        "File": "D:\\ghast\\downloads\\CLANNAD\\KOE\\0027\\Z002727552.ogg",
        "Text": "はは、これは面白い絵だなぁ。あのともやが、女の尻に敷かれてるなんて",
        "Name": "担任"
    },
    {
        "File": "D:\\ghast\\downloads\\CLANNAD\\KOE\\0027\\Z002727555.ogg",
        "Text": "うん？  なんだ、おまえたち、付き合ってるのか",
        "Name": "担任"
    },
    {
        "File": "D:\\ghast\\downloads\\CLANNAD\\KOE\\0027\\Z002727558.ogg",
        "Text": "ともやも丸くなったもんだなぁ",
        "Name": "担任"
    },
    {
        "File": "D:\\ghast\\downloads\\CLANNAD\\KOE\\0027\\Z002727559.ogg",
        "Text": "これは、進学させる余地も出てきたってもんだ",
        "Name": "担任"
    },
    {
        "File": "D:\\ghast\\downloads\\CLANNAD\\KOE\\0027\\Z002727561.ogg",
        "Text": "では、行こうか、ともやくん",
        "Name": "担任"
    },
    {
        "File": "D:\\ghast\\downloads\\CLANNAD\\KOE\\0027\\Z002727563.ogg",
        "Text": "こいつの家だよ。進路相談",
        "Name": "担任"
    },
    {
        "File": "D:\\ghast\\downloads\\CLANNAD\\KOE\\0027\\Z002727564.ogg",
        "Text": "君、一緒に来てくれるの？  だったら、こいつが逃げないで済みそうだから、ありがたいけど",
        "Name": "担任"
    },
    {
        "File": "D:\\ghast\\downloads\\CLANNAD\\KOE\\0027\\Z002727569.ogg",
        "Text": "君、よくこんな口の悪いのに耐えられるなぁ…",
        "Name": "担任"
    },
    {
        "File": "D:\\ghast\\downloads\\CLANNAD\\KOE\\0027\\Z002727571.ogg",
        "Text": "普通は、慣れる前に恐くて近寄れないと思うよ",
        "Name": "担任"
    },
    {
        "File": "D:\\ghast\\downloads\\CLANNAD\\KOE\\0027\\Z002727572.ogg",
        "Text": "よっぽど好きだったんだねぇ",
        "Name": "担任"
    },
    {
        "File": "D:\\ghast\\downloads\\CLANNAD\\KOE\\0027\\Z002727575.ogg",
        "Text": "いいじゃないか、おまえの彼女なんて興味津々だよ",
        "Name": "担任"
    },
    {
        "File": "D:\\ghast\\downloads\\CLANNAD\\KOE\\0027\\Z002727579.ogg",
        "Text": "よし。じゃ、いくか、ともや",
        "Name": "担任"
    },
    {
        "File": "D:\\ghast\\downloads\\CLANNAD\\KOE\\0027\\Z002727580.ogg",
        "Text": "なぁ、ともや",
        "Name": "担任"
    },
    {
        "File": "D:\\ghast\\downloads\\CLANNAD\\KOE\\0027\\Z002727581.ogg",
        "Text": "小さい頃から、親父さんひとりなんだろ？",
        "Name": "担任"
    },
    {
        "File": "D:\\ghast\\downloads\\CLANNAD\\KOE\\0027\\Z002727582.ogg",
        "Text": "苦労されたんだろうなぁ",
        "Name": "担任"
    },
    {
        "File": "D:\\ghast\\downloads\\CLANNAD\\KOE\\0027\\Z002727583.ogg",
        "Text": "男手ひとつで、おまえみたいな子、育てるなんてなぁ",
        "Name": "担任"
    },
    {
        "File": "D:\\ghast\\downloads\\CLANNAD\\KOE\\0027\\Z002727584.ogg",
        "Text": "でもまあ、おまえも人並みに彼女を作って、人並みに学園生活を謳歌してるみたいだしな…",
        "Name": "担任"
    },
    {
        "File": "D:\\ghast\\downloads\\CLANNAD\\KOE\\0027\\Z002727585.ogg",
        "Text": "このまま、親に心配かけないよう、進学しないと駄目だぞ？",
        "Name": "担任"
    },
    {
        "File": "D:\\ghast\\downloads\\CLANNAD\\KOE\\0027\\Z002727586.ogg",
        "Text": "いいから、いくぞ",
        "Name": "担任"
    },
    {
        "File": "D:\\ghast\\downloads\\CLANNAD\\KOE\\0027\\Z002727587.ogg",
        "Text": "じゃ、中で待たせてもらう",
        "Name": "担任"
    },
    {
        "File": "D:\\ghast\\downloads\\CLANNAD\\KOE\\0027\\Z002727588.ogg",
        "Text": "それが仕事だ。明日の朝までだって、待つぞ",
        "Name": "担任"
    },
    {
        "File": "D:\\ghast\\downloads\\CLANNAD\\KOE\\0027\\Z002727589.ogg",
        "Text": "うん？",
        "Name": "担任"
    },
    {
        "File": "D:\\ghast\\downloads\\CLANNAD\\KOE\\0027\\Z002727590.ogg",
        "Text": "なに？  本当か？",
        "Name": "担任"
    },
    {
        "File": "D:\\ghast\\downloads\\CLANNAD\\KOE\\0027\\Z002727591.ogg",
        "Text": "いや、なら、ここで待つ",
        "Name": "担任"
    },
    {
        "File": "D:\\ghast\\downloads\\CLANNAD\\KOE\\0027\\Z002727592.ogg",
        "Text": "ああ",
        "Name": "担任"
    },
    {
        "File": "D:\\ghast\\downloads\\CLANNAD\\KOE\\0027\\Z002727593.ogg",
        "Text": "だから、いくらでも待つと言ってるだろ",
        "Name": "担任"
    },
    {
        "File": "D:\\ghast\\downloads\\CLANNAD\\KOE\\0027\\Z002727594.ogg",
        "Text": "おまえも一緒に待つんだぞ",
        "Name": "担任"
    },
    {
        "File": "D:\\ghast\\downloads\\CLANNAD\\KOE\\0027\\Z002727595.ogg",
        "Text": "何を言ってるんだ、おまえの家だろ？",
        "Name": "担任"
    },
    {
        "File": "D:\\ghast\\downloads\\CLANNAD\\KOE\\0027\\Z002727596.ogg",
        "Text": "入れなかったら、おまえだって、困るだろ",
        "Name": "担任"
    },
    {
        "File": "D:\\ghast\\downloads\\CLANNAD\\KOE\\0027\\Z002727597.ogg",
        "Text": "こらっ！",
        "Name": "担任"
    },
    {
        "File": "D:\\ghast\\downloads\\CLANNAD\\KOE\\0027\\Z002727630.ogg",
        "Text": "ですが、まだ彼は学生でして、保護者の意見も…",
        "Name": "担任"
    }
]