[
    {
        "File": "danshia007_001",
        "Text": "いくぞ",
        "Name": "男子学生Ａ"
    },
    {
        "File": "danshia007_002",
        "Text": "むぅぅぅぅぅーー……",
        "Name": "男子学生Ａ"
    },
    {
        "File": "danshia007_004",
        "Text": "はぁ、はぁ……思ったより神経を使うな、これ",
        "Name": "男子学生Ａ"
    },
    {
        "File": "danshia007_005",
        "Text": "ぶはっ！おまっ、いい加減にしろ！さっきから痛いんだよ！このぉぉぉっ！",
        "Name": "男子学生Ａ"
    },
    {
        "File": "danshia007_006",
        "Text": "ぶるぅあ！？",
        "Name": "男子学生Ａ"
    },
    {
        "File": "danshia007_007",
        "Text": "知るか！勝負の最中に気を抜く方が悪い！",
        "Name": "男子学生Ａ"
    },
    {
        "File": "danshia007_008",
        "Text": "ぐぇ！負けるかぁ！",
        "Name": "男子学生Ａ"
    },
    {
        "File": "danshia008_001",
        "Text": "いや、迷惑をかけてたのはこっちだから",
        "Name": "男子学生Ａ"
    },
    {
        "File": "danshia008_002",
        "Text": "俺たちも悪かったよ。本当にゴメン",
        "Name": "男子学生Ａ"
    },
    {
        "File": "danshia008_003",
        "Text": "スマン",
        "Name": "男子学生Ａ"
    },
    {
        "File": "danshia008_004",
        "Text": "そう言えば……ちゃんと話すのは初めてだな",
        "Name": "男子学生Ａ"
    },
    {
        "File": "danshia008_005",
        "Text": "俺は、相模大志だ。そんでこっちが",
        "Name": "男子学生Ａ"
    },
    {
        "File": "danshia010_001",
        "Text": "他にもかき氷とかもあったよな",
        "Name": "男子学生Ａ"
    },
    {
        "File": "danshia010_002",
        "Text": "実は結構美味かったんだけどな",
        "Name": "男子学生Ａ"
    },
    {
        "File": "danshia010_003",
        "Text": "能力を使わず、普通に作ったたこ焼きとかも売ってるし、舞台で発表するのは普通の方が多いんじゃないか？",
        "Name": "男子学生Ａ"
    },
    {
        "File": "danshia011_001",
        "Text": "ああ、アレか、三司さんや二条院さんが参加してるやつ",
        "Name": "男子学生Ａ"
    },
    {
        "File": "danshia011_002",
        "Text": "当日は客として行くからな",
        "Name": "男子学生Ａ"
    },
    {
        "File": "danshia011_003",
        "Text": "確かに。なんせ、メンバーが派手だもんな。知ってれば、俺も手伝いたかったぜ",
        "Name": "男子学生Ａ"
    },
    {
        "File": "danshia012_001",
        "Text": "すみませーん。注文いいですかー？",
        "Name": "男子学生Ａ"
    },
    {
        "File": "danshia012_002",
        "Text": "ん？ああ……俺は別に周防でも気にしないが",
        "Name": "男子学生Ａ"
    },
    {
        "File": "danshia012_003",
        "Text": "なんだよ、その反応",
        "Name": "男子学生Ａ"
    },
    {
        "File": "danshia012_004",
        "Text": "違うぞ！別に変な意味ではなくて！俺は女の子でなくても気にしないってだけで",
        "Name": "男子学生Ａ"
    },
    {
        "File": "danshia012_005",
        "Text": "そんな目をしたまま離れるな！せめて注文ぐらいは聞いていけってば！",
        "Name": "男子学生Ａ"
    },
    {
        "File": "danshia103_001",
        "Text": "おはよう",
        "Name": "男子学生Ａ"
    },
    {
        "File": "danshia103_002",
        "Text": "あー、はいはい。わかったよ",
        "Name": "男子学生Ａ"
    },
    {
        "File": "danshia103_003",
        "Text": "なんだよ、その不満げな声",
        "Name": "男子学生Ａ"
    },
    {
        "File": "danshia103_004",
        "Text": "じゃあ１人で頑張れ",
        "Name": "男子学生Ａ"
    },
    {
        "File": "danshia103_005",
        "Text": "ったく……はぁぁ……",
        "Name": "男子学生Ａ"
    },
    {
        "File": "danshia103_006",
        "Text": "ああ、ちょっと偏頭痛が……元からたまにあったんだ",
        "Name": "男子学生Ａ"
    },
    {
        "File": "danshia103_007",
        "Text": "吐き気がするほどじゃないんだ。少しすれば、すぐに治まる",
        "Name": "男子学生Ａ"
    },
    {
        "File": "danshia103_008",
        "Text": "アストラル使いの診察って、細かい検査までするから時間かかるからなぁ",
        "Name": "男子学生Ａ"
    },
    {
        "File": "danshia103_009",
        "Text": "できれば部屋でゆっくりしてたいんだよ",
        "Name": "男子学生Ａ"
    },
    {
        "File": "danshia103_010",
        "Text": "……はぁ……そうだな。薬をもらえるなら助かるし、一度診てもらうか",
        "Name": "男子学生Ａ"
    },
    {
        "File": "danshia103_011",
        "Text": "多分、俺も同じ結果になるだろうな……",
        "Name": "男子学生Ａ"
    },
    {
        "File": "danshia103_012",
        "Text": "んなわけあるかっ",
        "Name": "男子学生Ａ"
    },
    {
        "File": "danshia103_013",
        "Text": "わかったから、叫ぶな",
        "Name": "男子学生Ａ"
    },
    {
        "File": "danshia106_003",
        "Text": "否定しないのか！？",
        "Name": "男子学生Ａ"
    },
    {
        "File": "danshia106_004",
        "Text": "三司さんと付き合ってる……なんてことはないよな？",
        "Name": "男子学生Ａ"
    },
    {
        "File": "danshia106_005",
        "Text": "はっはっは",
        "Name": "男子学生Ａ"
    },
    {
        "File": "danshia106_007",
        "Text": "あやせ！？もう呼び捨てかよ！？",
        "Name": "男子学生Ａ"
    },
    {
        "File": "danshia106_008",
        "Text": "そりゃなあ……",
        "Name": "男子学生Ａ"
    },
    {
        "File": "danshia106_009",
        "Text": "そうだな。なんつーの？なにか好機があれば、全然ＯＫだとは思ってたけど",
        "Name": "男子学生Ａ"
    },
    {
        "File": "danshia106_010",
        "Text": "他のみんなも、同じような感じじゃないか？ま、中には本気ってヤツもいるだろうけど",
        "Name": "男子学生Ａ"
    },
    {
        "File": "danshia106_011",
        "Text": "彼女、プライベートな付き合いはせずに、笑ってスルーするタイプだったから",
        "Name": "男子学生Ａ"
    },
    {
        "File": "danshia106_012",
        "Text": "まさか、一方的な思い込みのストーカーとか？",
        "Name": "男子学生Ａ"
    },
    {
        "File": "danshia106_013",
        "Text": "そりゃそうだ",
        "Name": "男子学生Ａ"
    },
    {
        "File": "danshia106_014",
        "Text": "願ってはいても、本気でモーションをかけてたわけじゃないんだから",
        "Name": "男子学生Ａ"
    },
    {
        "File": "danshia106_015",
        "Text": "けど、まさか在原と……。文句を言える立場ではないってわかってはいるけど……羨ましいやら妬ましいやら",
        "Name": "男子学生Ａ"
    },
    {
        "File": "danshia106_016",
        "Text": "その余裕がさらにムカつく",
        "Name": "男子学生Ａ"
    },
    {
        "File": "danshia106_017",
        "Text": "隙があったら背中刺してやる",
        "Name": "男子学生Ａ"
    },
    {
        "File": "danshia106_018",
        "Text": "安心しろ、在原……人は簡単には死にはしない。特にこの学院なら、医療設備も多少はある",
        "Name": "男子学生Ａ"
    },
    {
        "File": "danshia106_019",
        "Text": "重要なのは、刺されるところをしっかり選ぶことだ",
        "Name": "男子学生Ａ"
    },
    {
        "File": "danshia106_020",
        "Text": "いいだろ、これぐらいの妬みはよ",
        "Name": "男子学生Ａ"
    },
    {
        "File": "danshia106_021",
        "Text": "ん？ああ、アレか。いつも通りの偏頭痛。薬も柿本先生に出してもらったよ",
        "Name": "男子学生Ａ"
    },
    {
        "File": "danshia106_022",
        "Text": "おう。バッチリよ",
        "Name": "男子学生Ａ"
    },
    {
        "File": "danshia106_023",
        "Text": "おかげで、この前の休みは完全に潰れたけどな",
        "Name": "男子学生Ａ"
    },
    {
        "File": "danshia106_024",
        "Text": "そうなんだよなー",
        "Name": "男子学生Ａ"
    },
    {
        "File": "danshia107_001",
        "Text": "……おはよう",
        "Name": "男子学生Ａ"
    },
    {
        "File": "danshia107_002",
        "Text": "いつもの偏頭痛が、今日はちょっとひどくてな",
        "Name": "男子学生Ａ"
    },
    {
        "File": "danshia107_003",
        "Text": "もしかしたら、明日は雨かもな",
        "Name": "男子学生Ａ"
    },
    {
        "File": "danshia107_004",
        "Text": "気圧が下がると、頭痛が辛くなる気がする",
        "Name": "男子学生Ａ"
    },
    {
        "File": "danshia107_005",
        "Text": "全然無関係で外れることもよくあるけどな。にしても……あー……",
        "Name": "男子学生Ａ"
    },
    {
        "File": "danshia107_006",
        "Text": "もらった分は、ちょうど昨日飲みきった",
        "Name": "男子学生Ａ"
    },
    {
        "File": "danshia107_007",
        "Text": "そうだなー……そうするか",
        "Name": "男子学生Ａ"
    },
    {
        "File": "danshia107_008",
        "Text": "それもアリかもしれないな",
        "Name": "男子学生Ａ"
    },
    {
        "File": "danshia107_009",
        "Text": "……俺、ちょっと先生のところに行ってくるわ",
        "Name": "男子学生Ａ"
    },
    {
        "File": "danshia107_010",
        "Text": "ガキじゃないんだ。そこまで心配してもらわなくてもいいよ。それに、もうすぐ授業も始まるぞ",
        "Name": "男子学生Ａ"
    },
    {
        "File": "danshia107_013",
        "Text": "心配してくれるのはありがたいが、ただの頭痛だ。１人で大丈夫だよ",
        "Name": "男子学生Ａ"
    },
    {
        "File": "danshia107_014",
        "Text": "ちょっと行ってくる",
        "Name": "男子学生Ａ"
    },
    {
        "File": "danshia303_001",
        "Text": "ホントだよな。俺らもバルーンアート失敗してたら、たぶんまだ引きずってるぜ",
        "Name": "男子学生Ａ"
    },
    {
        "File": "danshia303_002",
        "Text": "ああ、そうだ。周防たちの店もよかったぜ！",
        "Name": "男子学生Ａ"
    },
    {
        "File": "danshia303_003",
        "Text": "そうだその失言があった！だから違うって、変な意味はねえよ！",
        "Name": "男子学生Ａ"
    },
    {
        "File": "danshia303_004",
        "Text": "俺は単純にな？お前らの店がよかったぜっていうだけでっ",
        "Name": "男子学生Ａ"
    }
]