[
    {
        "File": "D:\\ghast\\downloads\\KANON\\KANON\\KANON_SE\\KOE\\0019\\Z001919034.ogg",
        "Text": "あっ…わたしまだパジャマだよっ…",
        "Name": "声"
    },
    {
        "File": "D:\\ghast\\downloads\\KANON\\KANON\\KANON_SE\\KOE\\0019\\Z001919035.ogg",
        "Text": "うー…本当に時間ないのに…",
        "Name": "声"
    },
    {
        "File": "D:\\ghast\\downloads\\KANON\\KANON\\KANON_SE\\KOE\\0019\\Z001919119.ogg",
        "Text": "…あら？",
        "Name": "声"
    },
    {
        "File": "D:\\ghast\\downloads\\KANON\\KANON\\KANON_SE\\KOE\\0019\\Z001919294.ogg",
        "Text": "…ゆういち",
        "Name": "声"
    },
    {
        "File": "D:\\ghast\\downloads\\KANON\\KANON\\KANON_SE\\KOE\\0019\\Z001919295.ogg",
        "Text": "…ゆういち",
        "Name": "声"
    },
    {
        "File": "D:\\ghast\\downloads\\KANON\\KANON\\KANON_SE\\KOE\\0019\\Z001919401.ogg",
        "Text": "そこの人っ！",
        "Name": "声"
    },
    {
        "File": "D:\\ghast\\downloads\\KANON\\KANON\\KANON_SE\\KOE\\0019\\Z001919403.ogg",
        "Text": "どいてっ！  どいてっ！",
        "Name": "声"
    },
    {
        "File": "D:\\ghast\\downloads\\KANON\\KANON\\KANON_SE\\KOE\\0020\\Z002020382.ogg",
        "Text": "\\m{B}君っ！",
        "Name": "声"
    },
    {
        "File": "D:\\ghast\\downloads\\KANON\\KANON\\KANON_SE\\KOE\\0020\\Z002020462.ogg",
        "Text": "きゃうっ",
        "Name": "声"
    },
    {
        "File": "D:\\ghast\\downloads\\KANON\\KANON\\KANON_SE\\KOE\\0007\\Z000707000.ogg",
        "Text": "…きゃっ",
        "Name": "声"
    },
    {
        "File": "D:\\ghast\\downloads\\KANON\\KANON\\KANON_SE\\KOE\\0021\\Z002121485.ogg",
        "Text": "あぅーっ…",
        "Name": "声"
    },
    {
        "File": "D:\\ghast\\downloads\\KANON\\KANON\\KANON_SE\\KOE\\0021\\Z002121486.ogg",
        "Text": "お腹すいたよぉ…",
        "Name": "声"
    },
    {
        "File": "D:\\ghast\\downloads\\KANON\\KANON\\KANON_SE\\KOE\\0021\\Z002121487.ogg",
        "Text": "簡単に食べられそうなもの…見あたらないよぉ…",
        "Name": "声"
    },
    {
        "File": "D:\\ghast\\downloads\\KANON\\KANON\\KANON_SE\\KOE\\0021\\Z002121488.ogg",
        "Text": "勝手にこんなパジャマ着せられてるし…",
        "Name": "声"
    },
    {
        "File": "D:\\ghast\\downloads\\KANON\\KANON\\KANON_SE\\KOE\\0021\\Z002121489.ogg",
        "Text": "あぅーっ…お腹ぐぅぐぅ言ってる…",
        "Name": "声"
    },
    {
        "File": "D:\\ghast\\downloads\\KANON\\KANON\\KANON_SE\\KOE\\0021\\Z002121490.ogg",
        "Text": "きゃあああああああああぁぁぁぁぁぁぁぁーーーーーーーーーーーッッ！！！！",
        "Name": "声"
    },
    {
        "File": "D:\\ghast\\downloads\\KANON\\KANON\\KANON_SE\\KOE\\0021\\Z002121923.ogg",
        "Text": "あはは…",
        "Name": "声"
    },
    {
        "File": "D:\\ghast\\downloads\\KANON\\KANON\\KANON_SE\\KOE\\0021\\Z002121924.ogg",
        "Text": "３、２…",
        "Name": "声"
    },
    {
        "File": "D:\\ghast\\downloads\\KANON\\KANON\\KANON_SE\\KOE\\0021\\Z002121925.ogg",
        "Text": "１…",
        "Name": "声"
    },
    {
        "File": "D:\\ghast\\downloads\\KANON\\KANON\\KANON_SE\\KOE\\0021\\Z002121927.ogg",
        "Text": "わあああぁぁぁーーっ！",
        "Name": "声"
    },
    {
        "File": "D:\\ghast\\downloads\\KANON\\KANON\\KANON_SE\\KOE\\0021\\Z002121960.ogg",
        "Text": "ゼロッ",
        "Name": "声"
    },
    {
        "File": "D:\\ghast\\downloads\\KANON\\KANON\\KANON_SE\\KOE\\0021\\Z002121962.ogg",
        "Text": "やったぁ",
        "Name": "声"
    },
    {
        "File": "D:\\ghast\\downloads\\KANON\\KANON\\KANON_SE\\KOE\\0022\\Z002222421.ogg",
        "Text": "ゆういち君っ！",
        "Name": "声"
    },
    {
        "File": "D:\\ghast\\downloads\\KANON\\KANON\\KANON_SE\\KOE\\0023\\Z002323001.ogg",
        "Text": "ごほっ",
        "Name": "声"
    },
    {
        "File": "D:\\ghast\\downloads\\KANON\\KANON\\KANON_SE\\KOE\\0023\\Z002323012.ogg",
        "Text": "ゆういちっ",
        "Name": "声"
    },
    {
        "File": "D:\\ghast\\downloads\\KANON\\KANON\\KANON_SE\\KOE\\0023\\Z002323331.ogg",
        "Text": "ごめーんっ",
        "Name": "声"
    },
    {
        "File": "D:\\ghast\\downloads\\KANON\\KANON\\KANON_SE\\KOE\\0023\\Z002323498.ogg",
        "Text": "ゆういち君っ！",
        "Name": "声"
    },
    {
        "File": "D:\\ghast\\downloads\\KANON\\KANON\\KANON_SE\\KOE\\0023\\Z002323499.ogg",
        "Text": "あっ…",
        "Name": "声"
    },
    {
        "File": "D:\\ghast\\downloads\\KANON\\KANON\\KANON_SE\\KOE\\0023\\Z002323609.ogg",
        "Text": "ゆういちーーーーーっ！！",
        "Name": "声"
    },
    {
        "File": "D:\\ghast\\downloads\\KANON\\KANON\\KANON_SE\\KOE\\0023\\Z002323626.ogg",
        "Text": "ゆういちーーーーーっ！！",
        "Name": "声"
    },
    {
        "File": "D:\\ghast\\downloads\\KANON\\KANON\\KANON_SE\\KOE\\0013\\Z001313223.ogg",
        "Text": "\\m{B}君っ",
        "Name": "声"
    },
    {
        "File": "D:\\ghast\\downloads\\KANON\\KANON\\KANON_SE\\KOE\\0010\\Z001010476.ogg",
        "Text": "イタイ～ッ",
        "Name": "声"
    },
    {
        "File": "D:\\ghast\\downloads\\KANON\\KANON\\KANON_SE\\KOE\\0001\\Z000101314.ogg",
        "Text": "…うにゅ",
        "Name": "声"
    },
    {
        "File": "D:\\ghast\\downloads\\KANON\\KANON\\KANON_SE\\KOE\\0010\\Z001010627.ogg",
        "Text": "わぁーーーーーーっ！",
        "Name": "声"
    },
    {
        "File": "D:\\ghast\\downloads\\KANON\\KANON\\KANON_SE\\KOE\\0010\\Z001010814.ogg",
        "Text": "ね、ゆういちーっ…",
        "Name": "声"
    },
    {
        "File": "D:\\ghast\\downloads\\KANON\\KANON\\KANON_SE\\KOE\\0014\\Z001414193.ogg",
        "Text": "ゆういちさん、いますかーっ",
        "Name": "声"
    },
    {
        "File": "D:\\ghast\\downloads\\KANON\\KANON\\KANON_SE\\KOE\\0018\\Z001818085.ogg",
        "Text": "ねぇ、倉田さん",
        "Name": "声"
    },
    {
        "File": "D:\\ghast\\downloads\\KANON\\KANON\\KANON_SE\\KOE\\0011\\Z001111173.ogg",
        "Text": "…お昼ご飯なに",
        "Name": "声"
    },
    {
        "File": "D:\\ghast\\downloads\\KANON\\KANON\\KANON_SE\\KOE\\0011\\Z001111174.ogg",
        "Text": "あぅ…",
        "Name": "声"
    },
    {
        "File": "D:\\ghast\\downloads\\KANON\\KANON\\KANON_SE\\KOE\\0001\\Z000101754.ogg",
        "Text": "あれ、どうしたの？",
        "Name": "声"
    },
    {
        "File": "D:\\ghast\\downloads\\KANON\\KANON\\KANON_SE\\KOE\\0004\\Z000404946.ogg",
        "Text": "…ゆういち君",
        "Name": "声"
    },
    {
        "File": "D:\\ghast\\downloads\\KANON\\KANON\\KANON_SE\\KOE\\0015\\Z001515092.ogg",
        "Text": "…\\m{B}さん…でしょうか",
        "Name": "声"
    },
    {
        "File": "D:\\ghast\\downloads\\KANON\\KANON\\KANON_SE\\KOE\\0004\\Z000404964.ogg",
        "Text": "…ゆういち君",
        "Name": "声"
    },
    {
        "File": "D:\\ghast\\downloads\\KANON\\KANON\\KANON_SE\\KOE\\0014\\Z001414833.ogg",
        "Text": "あー、舞ーっ、こんなところに居たんだぁっ",
        "Name": "声"
    },
    {
        "File": "D:\\ghast\\downloads\\KANON\\KANON\\KANON_SE\\KOE\\0026\\Z002626078.ogg",
        "Text": "ゆういちさんっ、ちょっといいですかっ",
        "Name": "声"
    },
    {
        "File": "D:\\ghast\\downloads\\KANON\\KANON\\KANON_SE\\KOE\\0026\\Z002626167.ogg",
        "Text": "待たれよ",
        "Name": "声"
    },
    {
        "File": "D:\\ghast\\downloads\\KANON\\KANON\\KANON_SE\\KOE\\0026\\Z002626339.ogg",
        "Text": "はい、水瀬です",
        "Name": "声"
    },
    {
        "File": "D:\\ghast\\downloads\\KANON\\KANON\\KANON_SE\\KOE\\0002\\Z000202516.ogg",
        "Text": "ゆういちっ",
        "Name": "声"
    },
    {
        "File": "D:\\ghast\\downloads\\KANON\\KANON\\KANON_SE\\KOE\\0005\\Z000505045.ogg",
        "Text": "…ゆういち君",
        "Name": "声"
    },
    {
        "File": "D:\\ghast\\downloads\\KANON\\KANON\\KANON_SE\\KOE\\0028\\Z002828082.ogg",
        "Text": "学校、さぼってる人発見",
        "Name": "声"
    },
    {
        "File": "D:\\ghast\\downloads\\KANON\\KANON\\KANON_SE\\KOE\\0028\\Z002828084.ogg",
        "Text": "そうだね。だったら、おあいこ",
        "Name": "声"
    },
    {
        "File": "D:\\ghast\\downloads\\KANON\\KANON\\KANON_SE\\KOE\\0005\\Z000505136.ogg",
        "Text": "わっ！",
        "Name": "声"
    },
    {
        "File": "D:\\ghast\\downloads\\KANON\\KANON\\KANON_SE\\KOE\\0005\\Z000505137.ogg",
        "Text": "わ、わ、わ、わっ！",
        "Name": "声"
    },
    {
        "File": "D:\\ghast\\downloads\\KANON\\KANON\\KANON_SE\\KOE\\0005\\Z000505138.ogg",
        "Text": "わ、わ、わ、わ、わっ…",
        "Name": "声"
    },
    {
        "File": "D:\\ghast\\downloads\\KANON\\KANON\\KANON_SE\\KOE\\0012\\Z001212596.ogg",
        "Text": "…ゆういちさん",
        "Name": "声"
    },
    {
        "File": "D:\\ghast\\downloads\\KANON\\KANON\\KANON_SE\\KOE\\0012\\Z001212597.ogg",
        "Text": "…朝ですよ、ゆういちさん",
        "Name": "声"
    },
    {
        "File": "D:\\ghast\\downloads\\KANON\\KANON\\KANON_SE\\KOE\\0005\\Z000505076.ogg",
        "Text": "ボクもだよ、ゆういち君",
        "Name": "声"
    },
    {
        "File": "D:\\ghast\\downloads\\KANON\\KANON\\KANON_SE\\KOE\\0005\\Z000505077.ogg",
        "Text": "もう…時間がないから…",
        "Name": "声"
    },
    {
        "File": "D:\\ghast\\downloads\\KANON\\KANON\\KANON_SE\\KOE\\0005\\Z000505078.ogg",
        "Text": "今日は、お別れを言いに来たんだよ…",
        "Name": "声"
    },
    {
        "File": "D:\\ghast\\downloads\\KANON\\KANON\\KANON_SE\\KOE\\0005\\Z000505079.ogg",
        "Text": "…見つけて、くれたんだね",
        "Name": "声"
    },
    {
        "File": "D:\\ghast\\downloads\\KANON\\KANON\\KANON_SE\\KOE\\0005\\Z000505080.ogg",
        "Text": "…ありがとう…",
        "Name": "声"
    },
    {
        "File": "D:\\ghast\\downloads\\KANON\\KANON\\KANON_SE\\KOE\\0008\\Z000808096.ogg",
        "Text": "おはようございますっ",
        "Name": "声"
    },
    {
        "File": "D:\\ghast\\downloads\\KANON\\KANON\\KANON_SE\\KOE\\0008\\Z000808182.ogg",
        "Text": "あの～、すみません～っ",
        "Name": "声"
    },
    {
        "File": "D:\\ghast\\downloads\\KANON\\KANON\\KANON_SE\\KOE\\0008\\Z000808183.ogg",
        "Text": "あ、あの～",
        "Name": "声"
    },
    {
        "File": "D:\\ghast\\downloads\\KANON\\KANON\\KANON_SE\\KOE\\0008\\Z000808184.ogg",
        "Text": "\\m{B}さん、いらっしゃいますか…？",
        "Name": "声"
    },
    {
        "File": "D:\\ghast\\downloads\\KANON\\KANON\\KANON_SE\\KOE\\0008\\Z000808186.ogg",
        "Text": "…あの～",
        "Name": "声"
    },
    {
        "File": "D:\\ghast\\downloads\\KANON\\KANON\\KANON_SE\\KOE\\0006\\Z000606470.ogg",
        "Text": "栞ちゃんっ！",
        "Name": "声"
    },
    {
        "File": "D:\\ghast\\downloads\\KANON\\KANON\\KANON_SE\\KOE\\0031\\Z003131285.ogg",
        "Text": "…ゆういち君",
        "Name": "声"
    },
    {
        "File": "D:\\ghast\\downloads\\KANON\\KANON\\KANON_SE\\KOE\\0008\\Z000808801.ogg",
        "Text": "来たら、ダメなんですか？",
        "Name": "声"
    },
    {
        "File": "D:\\ghast\\downloads\\KANON\\KANON\\KANON_SE\\KOE\\0008\\Z000808802.ogg",
        "Text": "大丈夫です。今日から学業再開ですから",
        "Name": "声"
    },
    {
        "File": "D:\\ghast\\downloads\\KANON\\KANON\\KANON_SE\\KOE\\0008\\Z000808803.ogg",
        "Text": "はい",
        "Name": "声"
    },
    {
        "File": "D:\\ghast\\downloads\\KANON\\KANON\\KANON_SE\\KOE\\0008\\Z000808804.ogg",
        "Text": "はい",
        "Name": "声"
    },
    {
        "File": "D:\\ghast\\downloads\\KANON\\KANON\\KANON_SE\\KOE\\0008\\Z000808805.ogg",
        "Text": "そんなこと言う人、嫌いですよ",
        "Name": "声"
    },
    {
        "File": "D:\\ghast\\downloads\\KANON\\KANON\\KANON_SE\\KOE\\0008\\Z000808806.ogg",
        "Text": "ちゃんと、覚えてますよ",
        "Name": "声"
    },
    {
        "File": "D:\\ghast\\downloads\\KANON\\KANON\\KANON_SE\\KOE\\0008\\Z000808807.ogg",
        "Text": "だから、ここに来たんですから",
        "Name": "声"
    },
    {
        "File": "D:\\ghast\\downloads\\KANON\\KANON\\KANON_SE\\KOE\\0008\\Z000808808.ogg",
        "Text": "ダメですよ、無理してでも食べてください",
        "Name": "声"
    },
    {
        "File": "D:\\ghast\\downloads\\KANON\\KANON\\KANON_SE\\KOE\\0008\\Z000808809.ogg",
        "Text": "折角、いっぱい買って来たんですから",
        "Name": "声"
    },
    {
        "File": "D:\\ghast\\downloads\\KANON\\KANON\\KANON_SE\\KOE\\0008\\Z000808810.ogg",
        "Text": "はい",
        "Name": "声"
    },
    {
        "File": "D:\\ghast\\downloads\\KANON\\KANON\\KANON_SE\\KOE\\0008\\Z000808811.ogg",
        "Text": "やっぱり、寒い時より暖かい時に食べた方がおいしいですから",
        "Name": "声"
    },
    {
        "File": "D:\\ghast\\downloads\\KANON\\KANON\\KANON_SE\\KOE\\0008\\Z000808812.ogg",
        "Text": "起こらないから奇跡っていうんです",
        "Name": "声"
    },
    {
        "File": "D:\\ghast\\downloads\\KANON\\KANON\\KANON_SE\\KOE\\0008\\Z000808813.ogg",
        "Text": "でも…",
        "Name": "声"
    },
    {
        "File": "D:\\ghast\\downloads\\KANON\\KANON\\KANON_SE\\KOE\\0008\\Z000808814.ogg",
        "Text": "私…嘘つきですよね…",
        "Name": "声"
    },
    {
        "File": "D:\\ghast\\downloads\\KANON\\KANON\\KANON_SE\\KOE\\0008\\Z000808815.ogg",
        "Text": "ゆういちさん…",
        "Name": "声"
    },
    {
        "File": "D:\\ghast\\downloads\\KANON\\KANON\\KANON_SE\\KOE\\0008\\Z000808816.ogg",
        "Text": "こんな時…",
        "Name": "声"
    },
    {
        "File": "D:\\ghast\\downloads\\KANON\\KANON\\KANON_SE\\KOE\\0008\\Z000808817.ogg",
        "Text": "こんな時は…泣いていいんですよね…？",
        "Name": "声"
    },
    {
        "File": "D:\\ghast\\downloads\\KANON\\KANON\\KANON_SE\\KOE\\0008\\Z000808818.ogg",
        "Text": "どうして、ですか…？",
        "Name": "声"
    },
    {
        "File": "D:\\ghast\\downloads\\KANON\\KANON\\KANON_SE\\KOE\\0008\\Z000808819.ogg",
        "Text": "あはは…そうです、よね",
        "Name": "声"
    },
    {
        "File": "D:\\ghast\\downloads\\KANON\\KANON\\KANON_SE\\KOE\\0033\\Z003333000.ogg",
        "Text": "…行こうよ",
        "Name": "声"
    },
    {
        "File": "D:\\ghast\\downloads\\KANON\\KANON\\KANON_SE\\KOE\\0033\\Z003333001.ogg",
        "Text": "…早く行こうよ",
        "Name": "声"
    },
    {
        "File": "D:\\ghast\\downloads\\KANON\\KANON\\KANON_SE\\KOE\\0033\\Z003333002.ogg",
        "Text": "…早く行かないと、日が暮れちゃうよ？",
        "Name": "声"
    },
    {
        "File": "D:\\ghast\\downloads\\KANON\\KANON\\KANON_SE\\KOE\\0033\\Z003333004.ogg",
        "Text": "買い物だよ、買い物",
        "Name": "声"
    },
    {
        "File": "D:\\ghast\\downloads\\KANON\\KANON\\KANON_SE\\KOE\\0033\\Z003333006.ogg",
        "Text": "うん。お母さんに頼まれた買い物",
        "Name": "声"
    },
    {
        "File": "D:\\ghast\\downloads\\KANON\\KANON\\KANON_SE\\KOE\\0033\\Z003333008.ogg",
        "Text": "ゆういち、一緒に行ってくれるって言ったよね？",
        "Name": "声"
    },
    {
        "File": "D:\\ghast\\downloads\\KANON\\KANON\\KANON_SE\\KOE\\0033\\Z003333010.ogg",
        "Text": "嘘つきはダメだよ。針千本飲ますよ",
        "Name": "声"
    },
    {
        "File": "D:\\ghast\\downloads\\KANON\\KANON\\KANON_SE\\KOE\\0033\\Z003333012.ogg",
        "Text": "だったら行こうよ。大丈夫、きっと寒くないよ",
        "Name": "声"
    },
    {
        "File": "D:\\ghast\\downloads\\KANON\\KANON\\KANON_SE\\KOE\\0033\\Z003333014.ogg",
        "Text": "だったら針千本。今は増量期間中で針千五百本",
        "Name": "声"
    },
    {
        "File": "D:\\ghast\\downloads\\KANON\\KANON\\KANON_SE\\KOE\\0033\\Z003333016.ogg",
        "Text": "うんっ",
        "Name": "声"
    },
    {
        "File": "D:\\ghast\\downloads\\KANON\\KANON\\KANON_SE\\KOE\\0033\\Z003333096.ogg",
        "Text": "…うぐっ…えぐ",
        "Name": "声"
    },
    {
        "File": "D:\\ghast\\downloads\\KANON\\KANON\\KANON_SE\\KOE\\0033\\Z003333097.ogg",
        "Text": "…お母さん…うぐっ",
        "Name": "声"
    },
    {
        "File": "D:\\ghast\\downloads\\KANON\\KANON\\KANON_SE\\KOE\\0033\\Z003333099.ogg",
        "Text": "…うぐ…えぐ",
        "Name": "声"
    }
]