[
    {
        "File": "fem_rur_00001",
        "Text": "お話は終わりましたー？",
        "Name": "ルリヲ"
    },
    {
        "File": "fem_rur_00002",
        "Text": "いくら待っても話終わらないのですもん",
        "Name": "ルリヲ"
    },
    {
        "File": "fem_rur_00004",
        "Text": "何のじゃありませんよー。今日から、新生弓張美術部が旗揚げされるのですからぁ。放課後になったら、すぐに先輩方のところに駆けつけるって約束じゃないっすかー",
        "Name": "ルリヲ"
    },
    {
        "File": "fem_rur_00005",
        "Text": "してましたよォ。なんですかー、咲崎先輩は覚えておられないのですかぁー",
        "Name": "ルリヲ"
    },
    {
        "File": "fem_rur_00006",
        "Text": "そうですよ。ステンドグラス作品、『櫻達の色彩の足跡』の完成祝いの時ですよぉ",
        "Name": "ルリヲ"
    },
    {
        "File": "fem_rur_00007",
        "Text": "あれを名付けるのなら『櫻達の灰色の足跡』じゃなくて、『櫻達の色彩の足跡』がふさわしいって",
        "Name": "ルリヲ"
    },
    {
        "File": "fem_rur_00008",
        "Text": "まぁ、いいんじゃないんですかー？　楽しかったし",
        "Name": "ルリヲ"
    },
    {
        "File": "fem_rur_00010",
        "Text": "さらに、打ち上げで、咲崎先輩が泥酔して、草薙ちゃんに抱きついた時もマジうけましたね！",
        "Name": "ルリヲ"
    },
    {
        "File": "fem_rur_00015",
        "Text": "そんな事ないよ。鈴菜だってあったもん",
        "Name": "ルリヲ"
    },
    {
        "File": "fem_rur_00017",
        "Text": "でもさぁ、すげぇ、顔真っ赤になって俯いてたじゃん",
        "Name": "ルリヲ"
    },
    {
        "File": "fem_rur_00018",
        "Text": "そう？　すごい笑顔だったけど",
        "Name": "ルリヲ"
    },
    {
        "File": "fem_rur_00019",
        "Text": "まぁ、まぁ、その話はまた後ほどでー",
        "Name": "ルリヲ"
    },
    {
        "File": "fem_rur_00020",
        "Text": "それよりも美術部ですよぉ。今日から旗揚げなのですからぁ",
        "Name": "ルリヲ"
    },
    {
        "File": "fem_rur_00021",
        "Text": "そりゃ草薙ちゃんに決まってるじゃないですかぁ",
        "Name": "ルリヲ"
    },
    {
        "File": "fem_rur_00022",
        "Text": "全然っ、なんかすげぇ話をはぐらかされた感じですよ。ちょー嫌な感じです",
        "Name": "ルリヲ"
    },
    {
        "File": "fem_rur_00023",
        "Text": "よっしャー。んじゃ、職員室に行きますかー",
        "Name": "ルリヲ"
    },
    {
        "File": "fem_rur_00025",
        "Text": "先生帰ったんですかァ？",
        "Name": "ルリヲ"
    },
    {
        "File": "fem_rur_00027",
        "Text": "なんでもありません♪",
        "Name": "ルリヲ"
    },
    {
        "File": "fem_rur_00028",
        "Text": "え？　はい……",
        "Name": "ルリヲ"
    },
    {
        "File": "fem_rur_00029",
        "Text": "どうしたんですか？　なんかかなり急ぎで出てきましたけど",
        "Name": "ルリヲ"
    },
    {
        "File": "fem_rur_00030",
        "Text": "そうなの？",
        "Name": "ルリヲ"
    },
    {
        "File": "fem_rur_00031",
        "Text": "なるほど、それでいまだに目の敵にしているというわけかー。なるほどねぇ",
        "Name": "ルリヲ"
    },
    {
        "File": "fem_rur_00033",
        "Text": "そうかな？　草薙ちゃんって気分で早退しそうなイメージあるけど",
        "Name": "ルリヲ"
    },
    {
        "File": "fem_rur_00034",
        "Text": "だったら、どうしたんですかねぇ？",
        "Name": "ルリヲ"
    },
    {
        "File": "fem_rur_00035",
        "Text": "そうなんだ。雑用とかやらされるんだ",
        "Name": "ルリヲ"
    },
    {
        "File": "fem_rur_00036",
        "Text": "美術室の鍵じゃないですかー",
        "Name": "ルリヲ"
    },
    {
        "File": "fem_rur_00038",
        "Text": "そうと決まったら、美術室に出発ですよー",
        "Name": "ルリヲ"
    },
    {
        "File": "fem_rur_00039",
        "Text": "どうしました？",
        "Name": "ルリヲ"
    },
    {
        "File": "fem_rur_00040",
        "Text": "草薙ちゃーん",
        "Name": "ルリヲ"
    },
    {
        "File": "fem_rur_00041",
        "Text": "わーい、わーい。草薙ちゃん。チョー話分かるじゃないですかー",
        "Name": "ルリヲ"
    },
    {
        "File": "fem_rur_00042",
        "Text": "なんですかー？　草薙ちゃんったらぁ、ルリヲの育ったお乳が当たってぇ、興奮してしまいましたかー？　教師なのにー",
        "Name": "ルリヲ"
    },
    {
        "File": "fem_rur_00043",
        "Text": "がーん。お姉ちゃんのと比べられたァ……",
        "Name": "ルリヲ"
    },
    {
        "File": "fem_rur_00044",
        "Text": "ん？　どうしたんですかぁ？　草薙ちゃん。なんか止まってるんですけどー",
        "Name": "ルリヲ"
    },
    {
        "File": "fem_rur_00046",
        "Text": "部活勧誘しかありませんよー。バリバリやりますよー",
        "Name": "ルリヲ"
    },
    {
        "File": "fem_rur_00047",
        "Text": "コスプレするしかないじゃないですかー！　思いっきりエロ系やるのですよー",
        "Name": "ルリヲ"
    },
    {
        "File": "fem_rur_00048",
        "Text": "それでですよー。思いッきり写生大会を開くってんです。どう？　この案？",
        "Name": "ルリヲ"
    },
    {
        "File": "fem_rur_00050",
        "Text": "体操着って、色気ないなぁ。可愛いドロワースとかの方がいいじゃないですかー",
        "Name": "ルリヲ"
    },
    {
        "File": "fem_rur_00051",
        "Text": "いやいや、そこはやっぱり女の子をデッサンした方がみんなうれしいですってばー。可愛い女の子描くのルリヲも好きよ",
        "Name": "ルリヲ"
    },
    {
        "File": "fem_rur_00052",
        "Text": "なんか美術部のチラシって多色刷りが多いですねぇ。印刷とかじゃないんですねー",
        "Name": "ルリヲ"
    },
    {
        "File": "fem_rur_00053",
        "Text": "この当時はパソコンとか、まだ普及してなかったんですかねぇ",
        "Name": "ルリヲ"
    },
    {
        "File": "fem_rur_00054",
        "Text": "便利？　けど多色刷りとか大変そうですよ？",
        "Name": "ルリヲ"
    },
    {
        "File": "fem_rur_00056",
        "Text": "そうなんだろうねぇ",
        "Name": "ルリヲ"
    },
    {
        "File": "fem_rur_00057",
        "Text": "現物見せてもらえなかったからねぇ。しかし我が姉ながら想像を絶する出来だ",
        "Name": "ルリヲ"
    },
    {
        "File": "fem_rur_00058",
        "Text": "これもリトグラフですか？",
        "Name": "ルリヲ"
    },
    {
        "File": "fem_rur_00059",
        "Text": "ふーん。お姉ちゃんの絵ってこんなだったんですねぇ",
        "Name": "ルリヲ"
    },
    {
        "File": "fem_rur_00062",
        "Text": "そうだよぉ。躊躇してるの草薙ちゃんだけなんですからー",
        "Name": "ルリヲ"
    },
    {
        "File": "fem_rur_00063",
        "Text": "わくわくするねぇ",
        "Name": "ルリヲ"
    },
    {
        "File": "fem_rur_00064",
        "Text": "そうだねぇ。せっかくだから、私達も美術部の歴史に残る様な作品が作りたいですねぇ",
        "Name": "ルリヲ"
    },
    {
        "File": "fem_rur_00065",
        "Text": "そうですよー。里奈お姉ちゃんが出来たんだから、妹のルリヲにも出来ますよー",
        "Name": "ルリヲ"
    },
    {
        "File": "fem_rur_00066",
        "Text": "たしかに、リトグラフは興味ありますよねぇ",
        "Name": "ルリヲ"
    },
    {
        "File": "fem_rur_00067",
        "Text": "んじゃ、すぐにでも制作にっ",
        "Name": "ルリヲ"
    },
    {
        "File": "fem_rur_00068",
        "Text": "それだったら安く上がりそうだねぇ",
        "Name": "ルリヲ"
    },
    {
        "File": "fem_rur_00069",
        "Text": "石版使いたーい",
        "Name": "ルリヲ"
    },
    {
        "File": "fem_rur_00070",
        "Text": "そうだよ。先生は今教員だから、朝だって通勤ラッシュの時間なはずですし",
        "Name": "ルリヲ"
    },
    {
        "File": "fem_rur_00071",
        "Text": "えー、すぐにでも作業入りたいよー",
        "Name": "ルリヲ"
    },
    {
        "File": "fem_rur_00072",
        "Text": "おおっ。一名だけという事は、そいつぁ勝負という事ですねー",
        "Name": "ルリヲ"
    },
    {
        "File": "fem_rur_00073",
        "Text": "あ、グリースペンシルって名前だったんですか、その紙がぐるぐる巻いてあって、糸で引っ張ると中の芯が出てくるやつ",
        "Name": "ルリヲ"
    },
    {
        "File": "fem_rur_00074",
        "Text": "油性だったら何でも描けるわけじゃないのですかー？",
        "Name": "ルリヲ"
    },
    {
        "File": "fem_rur_00075",
        "Text": "リトグラフってアルミ板に直接描き込むと思ってました",
        "Name": "ルリヲ"
    },
    {
        "File": "fem_rur_00076",
        "Text": "一枚で一色か……、最終的にチラシの色って、何色までつかって良いのですか？",
        "Name": "ルリヲ"
    },
    {
        "File": "fem_rur_00077",
        "Text": "グラデーションは？",
        "Name": "ルリヲ"
    },
    {
        "File": "fem_rur_00078",
        "Text": "なるほど、グラデーションはOKなのですね。ふむふむ",
        "Name": "ルリヲ"
    },
    {
        "File": "fem_rur_00080",
        "Text": "おぉ、とうとう対決の時だねぇ",
        "Name": "ルリヲ"
    },
    {
        "File": "fem_rur_00081",
        "Text": "鈴菜はどうなのさぁ",
        "Name": "ルリヲ"
    },
    {
        "File": "fem_rur_00082",
        "Text": "鈴菜は相変わらず絵が上手いねぇ",
        "Name": "ルリヲ"
    },
    {
        "File": "fem_rur_00083",
        "Text": "私のはこんな感じですよー",
        "Name": "ルリヲ"
    },
    {
        "File": "fem_rur_00085",
        "Text": "鈴菜も私も師匠は里奈お姉ちゃんなのですよー",
        "Name": "ルリヲ"
    },
    {
        "File": "fem_rur_00086",
        "Text": "何がですかー？",
        "Name": "ルリヲ"
    },
    {
        "File": "fem_rur_00087",
        "Text": "あっ！！",
        "Name": "ルリヲ"
    },
    {
        "File": "fem_rur_00089",
        "Text": "そういう事言う可能性があるから、里奈お姉ちゃんにできる限り、草薙ちゃんの前では実力は隠しておけって言われたんだよ",
        "Name": "ルリヲ"
    },
    {
        "File": "fem_rur_00090",
        "Text": "そうかなぁ？　先輩後輩の関係でも教えるとかあると思うけど？",
        "Name": "ルリヲ"
    },
    {
        "File": "fem_rur_00092",
        "Text": "本当に？　突然、匙とか投げないよね",
        "Name": "ルリヲ"
    },
    {
        "File": "fem_rur_00093",
        "Text": "やったね！　言質取れたぞ！",
        "Name": "ルリヲ"
    },
    {
        "File": "fem_rur_00094",
        "Text": "なんですかー。今日決めるんじゃないんですかー？",
        "Name": "ルリヲ"
    },
    {
        "File": "fem_rur_00095",
        "Text": "それじゃ、部員勧誘の時期が終わっちゃいますよー",
        "Name": "ルリヲ"
    },
    {
        "File": "fem_rur_00096",
        "Text": "手伝うよ",
        "Name": "ルリヲ"
    },
    {
        "File": "fem_rur_00097",
        "Text": "「「先生と顔を合わせづらい？",
        "Name": "一同"
    },
    {
        "File": "fem_rur_00098",
        "Text": "そうですよー。昨日はじまったばかりの美術部なのにどうしたのですか？",
        "Name": "ルリヲ"
    },
    {
        "File": "fem_rur_00099",
        "Text": "前の時？",
        "Name": "ルリヲ"
    },
    {
        "File": "fem_rur_00100",
        "Text": "前って何ですかー。ルリヲ気になるなぁ",
        "Name": "ルリヲ"
    },
    {
        "File": "fem_rur_00101",
        "Text": "え？　もしかして草薙ちゃん襲ってきたとか？",
        "Name": "ルリヲ"
    },
    {
        "File": "fem_rur_00102",
        "Text": "咲崎先輩がちゃんと説明しないと。草薙ちゃん強姦魔疑惑ですよ",
        "Name": "ルリヲ"
    },
    {
        "File": "fem_rur_00103",
        "Text": "どっちにしろ。聞けないのならルリヲは草薙ちゃんに直接聞いちゃうんだけどね",
        "Name": "ルリヲ"
    },
    {
        "File": "fem_rur_00104",
        "Text": "とか言ってー、本当は咲崎先輩と草薙ちゃんだけの秘密があるのが許せないんじゃないですかー？",
        "Name": "ルリヲ"
    },
    {
        "File": "fem_rur_00106",
        "Text": "だってぇ、お祝いじゃないですかー。もりあがるかなぁ。とか思って",
        "Name": "ルリヲ"
    },
    {
        "File": "fem_rur_00107",
        "Text": "なになに？　介抱するていで、胸とか、もみもみっ、とかやってきた系ですかー？",
        "Name": "ルリヲ"
    },
    {
        "File": "fem_rur_00108",
        "Text": "あの屋敷古そうだもんねぇ",
        "Name": "ルリヲ"
    },
    {
        "File": "fem_rur_00109",
        "Text": "お、オナニーですかー。ほー。オナニーですカァ……",
        "Name": "ルリヲ"
    },
    {
        "File": "fem_rur_00110",
        "Text": "あ、あの草薙ちゃんがカー。ナ、なるほど",
        "Name": "ルリヲ"
    },
    {
        "File": "fem_rur_00112",
        "Text": "うれしい？　ええ？　なんでですかー？",
        "Name": "ルリヲ"
    },
    {
        "File": "fem_rur_00115",
        "Text": "そんな鈴菜はどうなんですかー？　草薙ちゃんにどう思われたい？",
        "Name": "ルリヲ"
    },
    {
        "File": "fem_rur_00116",
        "Text": "あれ？　どうしたの？　いきなり黙っちゃって……",
        "Name": "ルリヲ"
    },
    {
        "File": "fem_rur_00117",
        "Text": "……",
        "Name": "ルリヲ"
    },
    {
        "File": "fem_rur_00118",
        "Text": "いや、別に何でもないよ",
        "Name": "ルリヲ"
    },
    {
        "File": "fem_rur_00119",
        "Text": "ポジティブですねぇ",
        "Name": "ルリヲ"
    },
    {
        "File": "fem_rur_00120",
        "Text": "あー、そうかー。それ考えたらルリヲも同じですかねー",
        "Name": "ルリヲ"
    },
    {
        "File": "fem_rur_00121",
        "Text": "なんかさ。草薙ちゃんって人は、達観した様なところがあってさ。だいたいの事には動じないというか、気にしないというか……",
        "Name": "ルリヲ"
    },
    {
        "File": "fem_rur_00122",
        "Text": "モテるからですかねー",
        "Name": "ルリヲ"
    },
    {
        "File": "fem_rur_00123",
        "Text": "ラッキースケベとか沢山あったのかもねぇ",
        "Name": "ルリヲ"
    },
    {
        "File": "fem_rur_00125",
        "Text": "草薙ちゃんがこの学校の生徒の時から知り合いだからねぇ",
        "Name": "ルリヲ"
    },
    {
        "File": "fem_rur_00126",
        "Text": "ま、咲崎先輩は草薙ちゃんのオナニー見たんだからさぁ。いいじゃないですかー。ルリヲだって見たかったですよー",
        "Name": "ルリヲ"
    },
    {
        "File": "fem_rur_00129",
        "Text": "あ、それもあったね",
        "Name": "ルリヲ"
    },
    {
        "File": "fem_rur_00130",
        "Text": "鈴菜には昔っから世話になってるからねぇ",
        "Name": "ルリヲ"
    },
    {
        "File": "fem_rur_00131",
        "Text": "そういえば、咲崎先輩って今朝、草薙ちゃんの家にいったんですよねぇ",
        "Name": "ルリヲ"
    },
    {
        "File": "fem_rur_00132",
        "Text": "何があったんですかぁ？",
        "Name": "ルリヲ"
    },
    {
        "File": "fem_rur_00133",
        "Text": "「「えええ！！　オナニーのおかずにしてると宣言した！？",
        "Name": "一同"
    },
    {
        "File": "fem_rur_00135",
        "Text": "なるほど、分かりました。そこで私に考えがあります！",
        "Name": "ルリヲ"
    },
    {
        "File": "fem_rur_00136",
        "Text": "先生の家に泊まりに行って、みんなで監視するというのはどうだろうか？",
        "Name": "ルリヲ"
    },
    {
        "File": "fem_rur_00137",
        "Text": "みんなで咲崎先輩と同じ現場を見るというのはどうだろうか？",
        "Name": "ルリヲ"
    },
    {
        "File": "fem_rur_00138",
        "Text": "そりゃ、咲崎先輩だけずるいからですよー。私達も見たいですっ",
        "Name": "ルリヲ"
    },
    {
        "File": "fem_rur_00140",
        "Text": "途中から願望じゃないですかー",
        "Name": "ルリヲ"
    },
    {
        "File": "fem_rur_00141",
        "Text": "わっ",
        "Name": "ルリヲ"
    },
    {
        "File": "fem_rur_00142",
        "Text": "え、えっと……写生の事でして……",
        "Name": "ルリヲ"
    },
    {
        "File": "fem_rur_00143",
        "Text": "そ、それはー",
        "Name": "ルリヲ"
    },
    {
        "File": "fem_rur_00144",
        "Text": "あ！！",
        "Name": "ルリヲ"
    },
    {
        "File": "fem_rur_00145",
        "Text": "それで恩田さんが入る事になったんだ。すごいなぁ",
        "Name": "ルリヲ"
    },
    {
        "File": "fem_rur_00146",
        "Text": "え！　美術部員が五人そろうって？　だったらこれで部に昇格するって事ですか？",
        "Name": "ルリヲ"
    },
    {
        "File": "fem_rur_00152",
        "Text": "ペンネームを使ってるんだよ",
        "Name": "ルリヲ"
    },
    {
        "File": "fem_rur_00153",
        "Text": "ア・ロウアワーキウイちゃん",
        "Name": "ルリヲ"
    },
    {
        "File": "fem_rur_00154",
        "Text": "そうですかー？　そう言ってもらえるとうれしいですねー",
        "Name": "ルリヲ"
    },
    {
        "File": "fem_rur_00157",
        "Text": "う゛……なんか肯定されると、むかつく",
        "Name": "ルリヲ"
    },
    {
        "File": "fem_rur_00159",
        "Text": "なんでですかー。恩田さんの絵すげぇのにー",
        "Name": "ルリヲ"
    },
    {
        "File": "fem_rur_00160",
        "Text": "そうだねぇ。恩田さんと直に勝負なんて燃えるねぇ",
        "Name": "ルリヲ"
    },
    {
        "File": "fem_rur_00162",
        "Text": "むむむ、恩田さんが言うのなら説得力ありまくりで、ちょっと緊張しますよー",
        "Name": "ルリヲ"
    },
    {
        "File": "fem_rur_00163",
        "Text": "誰にも負けませんよー",
        "Name": "ルリヲ"
    },
    {
        "File": "fem_rur_00164",
        "Text": "ルリヲは終わったよ",
        "Name": "ルリヲ"
    },
    {
        "File": "fem_rur_00165",
        "Text": "さぁ、さぁ、ルリヲの絵はどうですかー",
        "Name": "ルリヲ"
    },
    {
        "File": "fem_rur_00166",
        "Text": "いきなり大評価だ！　他は他は？",
        "Name": "ルリヲ"
    },
    {
        "File": "fem_rur_00167",
        "Text": "それだけなんですかー？",
        "Name": "ルリヲ"
    },
    {
        "File": "fem_rur_00168",
        "Text": "げぇぇっ、なんでモノクロの描画でそこまで分かるのですか！？",
        "Name": "ルリヲ"
    },
    {
        "File": "fem_rur_00171",
        "Text": "なんかちゃんと教えてくれる気があるのかなぁって",
        "Name": "ルリヲ"
    },
    {
        "File": "fem_rur_00172",
        "Text": "さらに言えばですねぇ",
        "Name": "ルリヲ"
    },
    {
        "File": "fem_rur_00174",
        "Text": "がーん。断言されてしまいました",
        "Name": "ルリヲ"
    },
    {
        "File": "fem_rur_00175",
        "Text": "おおっ、すごい評価",
        "Name": "ルリヲ"
    },
    {
        "File": "fem_rur_00176",
        "Text": "だったらルリヲの絵は褒められたので、ライバルとして見てくれるのですか？",
        "Name": "ルリヲ"
    },
    {
        "File": "fem_rur_00177",
        "Text": "むむむ、こうなったら、弓張三年間でムーア展受賞するしかない",
        "Name": "ルリヲ"
    },
    {
        "File": "fem_rur_00178",
        "Text": "弓張美術部を復活させたのであれば、その伝統も復活させるしかないですよねー",
        "Name": "ルリヲ"
    },
    {
        "File": "fem_rur_00183",
        "Text": "そんな事ないですよ。ルリヲは何度も恩田さんの絵を見てますからっ",
        "Name": "ルリヲ"
    },
    {
        "File": "fem_rur_00184",
        "Text": "これって……",
        "Name": "ルリヲ"
    },
    {
        "File": "fem_rur_00185",
        "Text": "描写が必要ないから、インキでの発色を確認した",
        "Name": "ルリヲ"
    },
    {
        "File": "fem_rur_00186",
        "Text": "うん……",
        "Name": "ルリヲ"
    },
    {
        "File": "fem_rur_00188",
        "Text": "たしかに、この絵もいつも恩田さんの絵から感じる独特な感覚はあるのだけど、それがとても弱い感じが……",
        "Name": "ルリヲ"
    },
    {
        "File": "fem_rur_00189",
        "Text": "どうしたのですかー。黙り込んで",
        "Name": "ルリヲ"
    },
    {
        "File": "fem_rur_00190",
        "Text": "うん、凡庸だ。って言い方、なんか自分に言い聞かせてるみたいだねぇ",
        "Name": "ルリヲ"
    },
    {
        "File": "fem_rur_00191",
        "Text": "青一色にしたのは、そういう部分もあるかもしれませんしねぇ",
        "Name": "ルリヲ"
    },
    {
        "File": "fem_rur_00192",
        "Text": "それもそうだね",
        "Name": "ルリヲ"
    },
    {
        "File": "fem_rur_00193",
        "Text": "ルリヲは？",
        "Name": "ルリヲ"
    },
    {
        "File": "fem_rur_00194",
        "Text": "うー、なんか都合の良い時だけそれなんですねー",
        "Name": "ルリヲ"
    },
    {
        "File": "fem_rur_00195",
        "Text": "んじゃ、急いでみんなで終わらせようっ",
        "Name": "ルリヲ"
    },
    {
        "File": "fem_rur_00196",
        "Text": "お手伝いにきましたよー",
        "Name": "ルリヲ"
    },
    {
        "File": "fem_rur_00197",
        "Text": "そうだよ。下心なんて乙女にあるわけがない。あるのは性欲だけだ！",
        "Name": "ルリヲ"
    },
    {
        "File": "fem_rur_00198",
        "Text": "まぁ、まぁ、草薙ちゃんゆるしてよ～。鈴菜は下心はないけど性欲はあるんだよ",
        "Name": "ルリヲ"
    },
    {
        "File": "fem_rur_00199",
        "Text": "なんで閉めるんですかー。ひどいじゃないですかー",
        "Name": "ルリヲ"
    },
    {
        "File": "fem_rur_00200",
        "Text": "ルリヲはいいんだねー",
        "Name": "ルリヲ"
    },
    {
        "File": "fem_rur_00202",
        "Text": "やっぱり手伝いに来て良かったじゃないですかー",
        "Name": "ルリヲ"
    },
    {
        "File": "fem_rur_00203",
        "Text": "だったら、ルリヲ達はあるのですかー？",
        "Name": "ルリヲ"
    },
    {
        "File": "fem_rur_00204",
        "Text": "いやいや、それはマジですよ。鈴菜の男性嫌いは半端ないですからねぇ",
        "Name": "ルリヲ"
    },
    {
        "File": "fem_rur_00206",
        "Text": "うわぁ……、すごいよ。これっ。草薙ちゃんっッ",
        "Name": "ルリヲ"
    },
    {
        "File": "fem_rur_00207",
        "Text": "真っ赤すぎだよ。鈴菜",
        "Name": "ルリヲ"
    },
    {
        "File": "fem_rur_00208",
        "Text": "って！　めっちゃ血出てるよー",
        "Name": "ルリヲ"
    },
    {
        "File": "fem_rur_00209",
        "Text": "軟膏もってるから、これつけよう。鈴菜",
        "Name": "ルリヲ"
    },
    {
        "File": "fem_rur_00211",
        "Text": "へ？　なんでそこでア・ロウアワーキウイが？",
        "Name": "ルリヲ"
    },
    {
        "File": "fem_rur_00212",
        "Text": "な、何故それをっっ",
        "Name": "ルリヲ"
    },
    {
        "File": "fem_rur_00215",
        "Text": "特集ってほどじゃないですよ。一頁だったし、単に気に入ってくれた批評家の人がいてくれたのでページ割いてくれただけですよ？",
        "Name": "ルリヲ"
    },
    {
        "File": "fem_rur_00216",
        "Text": "まぁ、若いから目立つだけかもしれませんし",
        "Name": "ルリヲ"
    },
    {
        "File": "fem_rur_00218",
        "Text": "さすが草薙ちゃん。ルリヲの微妙な気持ちが分かってくれるんだねぇ",
        "Name": "ルリヲ"
    },
    {
        "File": "fem_rur_00219",
        "Text": "それは気に入ってるし！　恥ずかしくないじゃん！　アホかよ！",
        "Name": "ルリヲ"
    },
    {
        "File": "fem_rur_00220",
        "Text": "草薙ちゃんの若い頃はルリヲよりも凄い活躍だったから、ルリヲの微妙な気持ちを分かってくれると思ったのにぃ",
        "Name": "ルリヲ"
    },
    {
        "File": "fem_rur_00222",
        "Text": "いきなり話の腰折った。恥ずかしがってる",
        "Name": "ルリヲ"
    },
    {
        "File": "fem_rur_00223",
        "Text": "さてさて、作業開始ですよー",
        "Name": "ルリヲ"
    },
    {
        "File": "fem_rur_00224",
        "Text": "……",
        "Name": "ルリヲ"
    },
    {
        "File": "fem_rur_00225",
        "Text": "……",
        "Name": "ルリヲ"
    },
    {
        "File": "fem_rur_00226",
        "Text": "え？　もう終わり？",
        "Name": "ルリヲ"
    },
    {
        "File": "fem_rur_00227",
        "Text": "あれ？　明日が〆切りって、明日の終わりまでじゃないの？",
        "Name": "ルリヲ"
    },
    {
        "File": "fem_rur_00228",
        "Text": "明日の朝にはアルミ板に転写ですかぁ。なるほど実質今日が〆切りなのですねぇ",
        "Name": "ルリヲ"
    },
    {
        "File": "fem_rur_00229",
        "Text": "まぁねぇ。でもさぁ。手加えるとキリがなくて",
        "Name": "ルリヲ"
    },
    {
        "File": "fem_rur_00230",
        "Text": "しょうがないねぇ。とりあえず後片付けでもしようかー",
        "Name": "ルリヲ"
    },
    {
        "File": "fem_rur_00231",
        "Text": "ん？　あの音",
        "Name": "ルリヲ"
    },
    {
        "File": "fem_rur_00232",
        "Text": "今日、実は合宿があってさぁ",
        "Name": "ルリヲ"
    },
    {
        "File": "fem_rur_00233",
        "Text": "それだったら、今、藍先生は帰宅中じゃないかなぁ",
        "Name": "ルリヲ"
    },
    {
        "File": "fem_rur_00236",
        "Text": "さすが、藍先生、話が分かるなぁ～",
        "Name": "ルリヲ"
    },
    {
        "File": "fem_rur_00237",
        "Text": "え？　鈴菜って首席入学だったの？",
        "Name": "ルリヲ"
    },
    {
        "File": "fem_rur_00238",
        "Text": "あれってくじ引きとかじゃないんだ",
        "Name": "ルリヲ"
    },
    {
        "File": "fem_rur_00239",
        "Text": "お好み焼きとか？",
        "Name": "ルリヲ"
    },
    {
        "File": "fem_rur_00240",
        "Text": "アレとはなんですかー",
        "Name": "ルリヲ"
    },
    {
        "File": "fem_rur_00242",
        "Text": "水炊きだ～",
        "Name": "ルリヲ"
    },
    {
        "File": "fem_rur_00243",
        "Text": "白濁した汁って？",
        "Name": "ルリヲ"
    },
    {
        "File": "fem_rur_00244",
        "Text": "それ今度食べてみたい",
        "Name": "ルリヲ"
    },
    {
        "File": "fem_rur_00246",
        "Text": "んぇ？　いきなりむせ込んでどうしたの？",
        "Name": "ルリヲ"
    },
    {
        "File": "fem_rur_00247",
        "Text": "え？",
        "Name": "ルリヲ"
    },
    {
        "File": "fem_rur_00248",
        "Text": "わぁ、ありがとう。草薙ちゃん",
        "Name": "ルリヲ"
    },
    {
        "File": "fem_rur_00250",
        "Text": "食べますよ～",
        "Name": "ルリヲ"
    },
    {
        "File": "fem_rur_00251",
        "Text": "まぁ、鈴菜はお嬢だからねぇ",
        "Name": "ルリヲ"
    },
    {
        "File": "fem_rur_00253",
        "Text": "……",
        "Name": "ルリヲ"
    },
    {
        "File": "fem_rur_00254",
        "Text": "水引きとローラーの圧と速度で結構変わりますからねぇ",
        "Name": "ルリヲ"
    },
    {
        "File": "fem_rur_00255",
        "Text": "何度かやった事はありますからなぁ",
        "Name": "ルリヲ"
    },
    {
        "File": "fem_rur_00258",
        "Text": "乾いてますねぇ",
        "Name": "ルリヲ"
    },
    {
        "File": "fem_rur_00259",
        "Text": "それでは作業を開始しましょう",
        "Name": "ルリヲ"
    },
    {
        "File": "fem_rur_00260",
        "Text": "鈴菜は気が回る娘なんだよ",
        "Name": "ルリヲ"
    },
    {
        "File": "fem_rur_00261",
        "Text": "ルリヲは、絵を描く事が一番好きだからいいんだけど、そうじゃない娘達には酷かもしれないよね",
        "Name": "ルリヲ"
    },
    {
        "File": "fem_rur_00262",
        "Text": "草薙ちゃんの側にいる人達は、みんなそんな想いを持っているんだと思うよ",
        "Name": "ルリヲ"
    },
    {
        "File": "fem_rur_00263",
        "Text": "さぁ、それは、自分の胸に手を当てて考えてみる事だねぇ",
        "Name": "ルリヲ"
    },
    {
        "File": "fem_rur_00264",
        "Text": "嘘つきだなぁ。草薙ちゃんはさ",
        "Name": "ルリヲ"
    },
    {
        "File": "fem_rur_00265",
        "Text": "ま、ルリヲには草薙ちゃんの気持ちが少し分かるよ",
        "Name": "ルリヲ"
    },
    {
        "File": "fem_rur_00266",
        "Text": "芸術家ってヤツは、いつでも溢れる感情で埋め尽くされている",
        "Name": "ルリヲ"
    },
    {
        "File": "fem_rur_00267",
        "Text": "両手が塞がっちゃうほどの感情を持つ者にとって、誰かの想いなんて新しく持てない……",
        "Name": "ルリヲ"
    },
    {
        "File": "fem_rur_00268",
        "Text": "そう普通の人は思う",
        "Name": "ルリヲ"
    },
    {
        "File": "fem_rur_00270",
        "Text": "芸術家はあらゆる想いを呑み込んで、美として昇華する",
        "Name": "ルリヲ"
    },
    {
        "File": "fem_rur_00271",
        "Text": "だから、巨大な美を宿す芸術家と関われば人は不幸になる",
        "Name": "ルリヲ"
    },
    {
        "File": "fem_rur_00272",
        "Text": "芸術史を見れば、そんな昔話で溢れている",
        "Name": "ルリヲ"
    },
    {
        "File": "fem_rur_00273",
        "Text": "芸術家の本質は危険である事",
        "Name": "ルリヲ"
    },
    {
        "File": "fem_rur_00274",
        "Text": "芸術という渦は、あらゆる人々の感情を呑み込むのだからさ……",
        "Name": "ルリヲ"
    },
    {
        "File": "fem_rur_00275",
        "Text": "うん、それはさ、草薙ちゃんは優しいからだよ",
        "Name": "ルリヲ"
    },
    {
        "File": "fem_rur_00276",
        "Text": "草薙ちゃんは私達の先生である事を選んだんでしょ？",
        "Name": "ルリヲ"
    },
    {
        "File": "fem_rur_00277",
        "Text": "先生は、自分の生徒を呑み込む様な事がない",
        "Name": "ルリヲ"
    },
    {
        "File": "fem_rur_00278",
        "Text": "それどころか、教師とは寄り添う者だ",
        "Name": "ルリヲ"
    },
    {
        "File": "fem_rur_00279",
        "Text": "芸術家と真逆だよね",
        "Name": "ルリヲ"
    },
    {
        "File": "fem_rur_00280",
        "Text": "なんだよ！　でも正解じゃん！",
        "Name": "ルリヲ"
    },
    {
        "File": "fem_rur_00282",
        "Text": "でもさ、もし草薙ちゃんが芸術家ではなく一教師として生きていくのなら、新しい想いを受け取るのもいいんじゃねぇの？",
        "Name": "ルリヲ"
    },
    {
        "File": "fem_rur_00283",
        "Text": "ルリヲちゃんはいつでも草薙ちゃんと恋人関係ウエルカムだぜって事かな？",
        "Name": "ルリヲ"
    },
    {
        "File": "fem_rur_00284",
        "Text": "手際がいいねぇ",
        "Name": "ルリヲ"
    },
    {
        "File": "fem_rur_00285",
        "Text": "あ、鈴菜",
        "Name": "ルリヲ"
    },
    {
        "File": "fem_rur_00286",
        "Text": "そうなん？　それよりも、作業続けちゃっているよ！　咲崎先輩も鈴菜も早く早く作業はじめようよ！",
        "Name": "ルリヲ"
    },
    {
        "File": "fem_rur_00287",
        "Text": "アルミ板にラッカーを垂らす手順だね",
        "Name": "ルリヲ"
    },
    {
        "File": "fem_rur_00289",
        "Text": "さぁ、次の作業はシリコンなのです。シリコンを薄め液で溶かすのです",
        "Name": "ルリヲ"
    },
    {
        "File": "fem_rur_00290",
        "Text": "なーんだ。そういう作業も生徒にやらせた方がいいよ",
        "Name": "ルリヲ"
    },
    {
        "File": "fem_rur_00291",
        "Text": "美術部員どれだけ集まるですかねー",
        "Name": "ルリヲ"
    },
    {
        "File": "fem_rur_00292",
        "Text": "そうですかねー",
        "Name": "ルリヲ"
    },
    {
        "File": "fem_rur_00293",
        "Text": "そうだねー。なんかチラシ完成する前に集まっちゃったねー",
        "Name": "ルリヲ"
    },
    {
        "File": "fem_rur_00294",
        "Text": "さっきから寧ちゃん空みてる",
        "Name": "ルリヲ"
    },
    {
        "File": "fem_rur_00295",
        "Text": "あ、本当だ",
        "Name": "ルリヲ"
    },
    {
        "File": "fem_rur_00296",
        "Text": "そうだといいんだけどね",
        "Name": "ルリヲ"
    },
    {
        "File": "fem_rur_00299",
        "Text": "そうかな？",
        "Name": "ルリヲ"
    },
    {
        "File": "fem_rur_00300",
        "Text": "ううん。合っていると思いますよ",
        "Name": "ルリヲ"
    },
    {
        "File": "fem_rur_00301",
        "Text": "ルリヲのライバルが言っているのですから",
        "Name": "ルリヲ"
    },
    {
        "File": "fem_rur_00302",
        "Text": "なんで笑うんですかー。バカにしてますかー？",
        "Name": "ルリヲ"
    },
    {
        "File": "fem_rur_00303",
        "Text": "光栄すぎると笑うって、何ですかーそれー、寧ちゃーん",
        "Name": "ルリヲ"
    },
    {
        "File": "fem_rur_00304",
        "Text": "えーだって、受験がんばったんだしー。少しは休みたいじゃん",
        "Name": "ルリヲ"
    },
    {
        "File": "fem_rur_00305",
        "Text": "一番星って金星だっけ？",
        "Name": "ルリヲ"
    },
    {
        "File": "fem_rur_00306",
        "Text": "天気良かったからね",
        "Name": "ルリヲ"
    },
    {
        "File": "fem_rur_00307",
        "Text": "新月？",
        "Name": "ルリヲ"
    },
    {
        "File": "fem_rur_00308",
        "Text": "そっか、月が明るいと他の星が見えづらいもんね",
        "Name": "ルリヲ"
    },
    {
        "File": "fem_rur_00309",
        "Text": "何を言ってるのですか、寧ちゃんが色味変更してくれたからです",
        "Name": "ルリヲ"
    },
    {
        "File": "fem_rur_00310",
        "Text": "ありがと草薙ちゃん",
        "Name": "ルリヲ"
    },
    {
        "File": "fem_rur_00312",
        "Text": "ごめんね",
        "Name": "ルリヲ"
    },
    {
        "File": "fem_rur_00313",
        "Text": "私達も合いの手を入れるよ",
        "Name": "ルリヲ"
    },
    {
        "File": "fem_rur_00315",
        "Text": "なんで、最後までいないのですかっッ",
        "Name": "ルリヲ"
    },
    {
        "File": "fem_rur_00316",
        "Text": "実はー、生徒達の姿に感動して、涙を見せたくなかったとかですよねー",
        "Name": "ルリヲ"
    },
    {
        "File": "fem_rur_00317",
        "Text": "全然っ",
        "Name": "ルリヲ"
    },
    {
        "File": "fem_rur_00318",
        "Text": "私達よりもたばこですか！？　ヤニなのですか！？",
        "Name": "ルリヲ"
    },
    {
        "File": "fem_rur_00319",
        "Text": "はー、なるほどねぇ。草薙ちゃんは恥ずかしがってたわけですね",
        "Name": "ルリヲ"
    },
    {
        "File": "fem_rur_00321",
        "Text": "草薙ちゃーん",
        "Name": "ルリヲ"
    },
    {
        "File": "fem_rur_00322",
        "Text": "まぁ、咲崎先輩に比べれば覚えるスピーチなんか無いに等しかったけどねぇ",
        "Name": "ルリヲ"
    },
    {
        "File": "fem_rur_00323",
        "Text": "そうなんですかー。ルリヲはわりかし考えちゃいましたよー",
        "Name": "ルリヲ"
    },
    {
        "File": "fem_rur_00324",
        "Text": "展覧会の絵っていいですよねぇ。やっぱり絵は見られてなんぼですよ",
        "Name": "ルリヲ"
    },
    {
        "File": "fem_rur_00325",
        "Text": "ルリヲが公募に出すのもそういう事だもん。寧ちゃんは違うのですか？",
        "Name": "ルリヲ"
    },
    {
        "File": "fem_rur_00326",
        "Text": "はへ？　違うのですか？",
        "Name": "ルリヲ"
    },
    {
        "File": "fem_rur_00327",
        "Text": "なるほど、探求的なものですね",
        "Name": "ルリヲ"
    },
    {
        "File": "fem_rur_00328",
        "Text": "帰れコールですねー",
        "Name": "ルリヲ"
    },
    {
        "File": "fem_rur_00329",
        "Text": "たしかに、こいつはいろいろな感情が渦巻いてますからねぇ。一目だけって言うのはさびしすぎますよねー",
        "Name": "ルリヲ"
    },
    {
        "File": "fem_rur_00330",
        "Text": "みんなで手つなぎません？",
        "Name": "ルリヲ"
    },
    {
        "File": "fem_rur_00331",
        "Text": "なんとなく",
        "Name": "ルリヲ"
    },
    {
        "File": "fem_rur_00332",
        "Text": "ず、ずるいっ",
        "Name": "ルリヲ"
    },
    {
        "File": "fem_rur_00333",
        "Text": "いいのですか？",
        "Name": "ルリヲ"
    },
    {
        "File": "fem_rur_00334",
        "Text": "夏に合宿とかいいねぇ",
        "Name": "ルリヲ"
    },
    {
        "File": "fem_rur_10001",
        "Text": "うぉ！　草薙ちゃん！　いたの！？",
        "Name": "ルリヲ"
    },
    {
        "File": "fem_rur_10002",
        "Text": "おう！　それです！　今まで挑戦してきた中では一番大きいですよー",
        "Name": "ルリヲ"
    },
    {
        "File": "fem_rur_10003",
        "Text": "FIRST展狙いだからなのです",
        "Name": "ルリヲ"
    },
    {
        "File": "fem_rur_10004",
        "Text": "八月十八日から九月二十二日です",
        "Name": "ルリヲ"
    },
    {
        "File": "fem_rur_10005",
        "Text": "自分で組みました。それでも結構な値段ですけど……",
        "Name": "ルリヲ"
    },
    {
        "File": "fem_rur_10006",
        "Text": "いいえ、これはムーア展の前哨戦ですから",
        "Name": "ルリヲ"
    },
    {
        "File": "fem_rur_10007",
        "Text": "その通り！",
        "Name": "ルリヲ"
    },
    {
        "File": "fem_rur_10008",
        "Text": "その一人が私ですよ",
        "Name": "ルリヲ"
    },
    {
        "File": "fem_rur_10009",
        "Text": "とは言っても、ムーア展の最高賞の百分の一以下なんですけどね",
        "Name": "ルリヲ"
    },
    {
        "File": "fem_rur_10010",
        "Text": "分かってますよ。私はあそこで奨励賞しかもらった事ないんですもん",
        "Name": "ルリヲ"
    },
    {
        "File": "fem_rur_10012",
        "Text": "草薙ちゃんはFIRST展の理念って知ってる？",
        "Name": "ルリヲ"
    },
    {
        "File": "fem_rur_10014",
        "Text": "草薙ちゃんは出した事あるのですかー？",
        "Name": "ルリヲ"
    },
    {
        "File": "fem_rur_10015",
        "Text": "何か取れました？",
        "Name": "ルリヲ"
    },
    {
        "File": "fem_rur_10016",
        "Text": "な！　それって最高賞手前じゃないですか！",
        "Name": "ルリヲ"
    },
    {
        "File": "fem_rur_10017",
        "Text": "でも八十万円じゃありませんか！　すごい金額ですよ！",
        "Name": "ルリヲ"
    },
    {
        "File": "fem_rur_10018",
        "Text": "うわぁ……すごい嫌味",
        "Name": "ルリヲ"
    },
    {
        "File": "fem_rur_10019",
        "Text": "いや、草薙ちゃんの絵って市場に出ると一千万円余裕で超えるって聞きますよー",
        "Name": "ルリヲ"
    },
    {
        "File": "fem_rur_10021",
        "Text": "ほらほら、この絵、先生が文展で最初に特賞を取った有名な日本画、『火水』の落札価格見てくださいよ",
        "Name": "ルリヲ"
    },
    {
        "File": "fem_rur_10023",
        "Text": "史上最高絵画の祭典ムーア展にエントリーしたんですよ。そりゃその作品が高値で売り買いされる理由にもなりますって",
        "Name": "ルリヲ"
    },
    {
        "File": "fem_rur_10024",
        "Text": "今だったら市役所に飾られている『櫻日狂想』も『火水』と同等かそれ以上の価格だと言われています。だいたい二千万から三千万ぐらいが妥当だって話ですよ",
        "Name": "ルリヲ"
    },
    {
        "File": "fem_rur_10025",
        "Text": "当時は草薙ちゃんの絵の価格がまだ安かっただけだって",
        "Name": "ルリヲ"
    },
    {
        "File": "fem_rur_10026",
        "Text": "ムーア展であの夏目圭と競った名画。『蝶を夢む』ならば四千万以上するんじゃないですか？",
        "Name": "ルリヲ"
    },
    {
        "File": "fem_rur_10028",
        "Text": "だから草薙ちゃんだって同じじゃん",
        "Name": "ルリヲ"
    },
    {
        "File": "fem_rur_10030",
        "Text": "でも草薙ちゃんだったら、絶対ギャラリストさんからお声かかってますよね",
        "Name": "ルリヲ"
    },
    {
        "File": "fem_rur_10032",
        "Text": "いいなぁ、さすが草薙直哉ともなると言うことのレベルが違う……",
        "Name": "ルリヲ"
    },
    {
        "File": "fem_rur_10034",
        "Text": "え？　そうなんですか？",
        "Name": "ルリヲ"
    },
    {
        "File": "fem_rur_10035",
        "Text": "誰ですか？",
        "Name": "ルリヲ"
    },
    {
        "File": "fem_rur_10036",
        "Text": "えー！！　最高賞って三百万円を取ったのですかー！！",
        "Name": "ルリヲ"
    },
    {
        "File": "fem_rur_10037",
        "Text": "どれもめちゃくちゃ賞金が高いので有名な賞じゃないですか！！",
        "Name": "ルリヲ"
    },
    {
        "File": "fem_rur_10038",
        "Text": "え？　まじで？　その高額な最高賞の賞金っていくらなんですか？",
        "Name": "ルリヲ"
    },
    {
        "File": "fem_rur_10039",
        "Text": "まさかそれを取ったのですか！！",
        "Name": "ルリヲ"
    },
    {
        "File": "fem_rur_10041",
        "Text": "だとしても、それだけ賞金稼いでたら夏目圭さんって、弓張時代は相当お金持ちだったんじゃないですか？",
        "Name": "ルリヲ"
    },
    {
        "File": "fem_rur_10042",
        "Text": "や、やっぱり家が建つんだ……",
        "Name": "ルリヲ"
    },
    {
        "File": "fem_rur_10043",
        "Text": "わ、私ぐらいの年齢で、すでに有名ギャラリストがついてて、個展まで開いて、絵を売ってたって……",
        "Name": "ルリヲ"
    },
    {
        "File": "fem_rur_10044",
        "Text": "何でですか？",
        "Name": "ルリヲ"
    },
    {
        "File": "fem_rur_10046",
        "Text": "でもでも、草薙ちゃんだって、その夏目圭のライバルだったわけでしょ？",
        "Name": "ルリヲ"
    },
    {
        "File": "fem_rur_10047",
        "Text": "ちなみにお聞きしたいのですがー、もしかして夏目圭さんがFIRST展の最高賞を取ったのって私より若い時だったりします？",
        "Name": "ルリヲ"
    },
    {
        "File": "fem_rur_10048",
        "Text": "そ、そうなんだ……",
        "Name": "ルリヲ"
    },
    {
        "File": "fem_rur_10050",
        "Text": "うー、すげぇなぁ。あの二人",
        "Name": "ルリヲ"
    },
    {
        "File": "fem_rur_10051",
        "Text": "ルリヲとかあの頃はまだ小っちゃかったんで、夏目圭さんがそんなすげぇ芸術家だとは思わなかったよー",
        "Name": "ルリヲ"
    },
    {
        "File": "fem_rur_10052",
        "Text": "そうなん？　なんかそういう雰囲気な人に見えなかったけど？？",
        "Name": "ルリヲ"
    },
    {
        "File": "fem_rur_10053",
        "Text": "明るくていい人だったイメージしかありませんけど",
        "Name": "ルリヲ"
    },
    {
        "File": "fem_rur_10054",
        "Text": "全然想像出来ないわー",
        "Name": "ルリヲ"
    },
    {
        "File": "fem_rur_10055",
        "Text": "何かあったのですか？",
        "Name": "ルリヲ"
    },
    {
        "File": "fem_rur_10057",
        "Text": "なんじゃそりゃ？？　私なんてめちゃくちゃ勉強してやっとこさ入れたのに",
        "Name": "ルリヲ"
    },
    {
        "File": "fem_rur_10059",
        "Text": "そうなん？",
        "Name": "ルリヲ"
    },
    {
        "File": "fem_rur_10060",
        "Text": "そ、そうなんですか？",
        "Name": "ルリヲ"
    },
    {
        "File": "fem_rur_10061",
        "Text": "そんな気むずかしそうに見えなかったけど……",
        "Name": "ルリヲ"
    },
    {
        "File": "fem_rur_10062",
        "Text": "な、なんというか……聞くに恐ろしいぐらいの天才だ……",
        "Name": "ルリヲ"
    },
    {
        "File": "fem_rur_10063",
        "Text": "良く、弓張でついてこれましたねぇ",
        "Name": "ルリヲ"
    },
    {
        "File": "fem_rur_10064",
        "Text": "そうですよねぇ。ムーア展取っている人間が生徒なんか、すでに教授より偉いですからね。完全に教授と生徒のレベルが逆になりますな",
        "Name": "ルリヲ"
    },
    {
        "File": "fem_rur_10065",
        "Text": "なるほど……",
        "Name": "ルリヲ"
    },
    {
        "File": "fem_rur_10066",
        "Text": "うう……格好いいなぁ。私もそんな風になりたかった……",
        "Name": "ルリヲ"
    },
    {
        "File": "fem_rur_10067",
        "Text": "なんか舐められてる感じしかしねぇ！　すげぇむかつく！",
        "Name": "ルリヲ"
    },
    {
        "File": "fem_rur_10068",
        "Text": "ムキー。そんな事言ってられるのも今のうちだかんねーっッ！！",
        "Name": "ルリヲ"
    },
    {
        "File": "fem_rur_10069",
        "Text": "あー！！",
        "Name": "ルリヲ"
    },
    {
        "File": "fem_rur_10072",
        "Text": "うん、なんとかってどっかの大学で研究したら、６時間以下の睡眠は、効率が下がるから良くないって結果が出たんだってさ。お姉ちゃんから聞いた話なんで詳しくは知らないけれども",
        "Name": "ルリヲ"
    },
    {
        "File": "fem_rur_10073",
        "Text": "うんうん、寝るのも仕事だぜー",
        "Name": "ルリヲ"
    },
    {
        "File": "fem_rur_10090",
        "Text": "うう……くやしい。その栄冠に輝くのは、このア・ロウアワーキウイちゃんだったハズなのにぃ……",
        "Name": "ルリヲ"
    },
    {
        "File": "fem_rur_10094",
        "Text": "こちら？　こちらって……",
        "Name": "ルリヲ"
    },
    {
        "File": "fem_rur_10095",
        "Text": "み、宮崎みすゞ先生？",
        "Name": "ルリヲ"
    },
    {
        "File": "fem_rur_10097",
        "Text": "わっ、宮崎みすゞ先生！　私のPNとか覚えてくださっているのですか！",
        "Name": "ルリヲ"
    },
    {
        "File": "fem_rur_10098",
        "Text": "草薙ちゃん！　私、宮崎みすゞに認知されているんだよ！　すごくね？　巨匠だよ。世界的な巨匠が目にかけているとか凄すぎだろ！",
        "Name": "ルリヲ"
    },
    {
        "File": "fem_rur_10099",
        "Text": "ルリヲのPNは変じゃねぇっつーの！",
        "Name": "ルリヲ"
    },
    {
        "File": "fem_rur_10100",
        "Text": "“生のキウイ時間”って意味ですよ。かわいさヤバたんスわ",
        "Name": "ルリヲ"
    },
    {
        "File": "fem_rur_10101",
        "Text": "氷川ルリヲなのです",
        "Name": "ルリヲ"
    },
    {
        "File": "fem_rur_10102",
        "Text": "あ、もしかして分かっちゃいましたか？",
        "Name": "ルリヲ"
    },
    {
        "File": "fem_rur_10103",
        "Text": "秘密だしー",
        "Name": "ルリヲ"
    },
    {
        "File": "fem_rur_10105",
        "Text": "おやおや、今さら気がついたんすかー？",
        "Name": "ルリヲ"
    },
    {
        "File": "fem_rur_10108",
        "Text": "ムキー！　そんな事ありませんよー！　英単語さえいろいろ知ってれば出来るものなんですよ！",
        "Name": "ルリヲ"
    },
    {
        "File": "fem_rur_10109",
        "Text": "ま、まぁ、少しはお姉ちゃんに手伝ってもらったといいますかー",
        "Name": "ルリヲ"
    },
    {
        "File": "fem_rur_10110",
        "Text": "ガイシケーつーところに勤めているぐらいですからなぁ",
        "Name": "ルリヲ"
    },
    {
        "File": "fem_rur_10113",
        "Text": "う゛……頼む前に断られた",
        "Name": "ルリヲ"
    },
    {
        "File": "fem_rur_10115",
        "Text": "和解完了って事で、さぁ、パーティを続けましょう！",
        "Name": "ルリヲ"
    },
    {
        "File": "fem_rur_10116",
        "Text": "今後よろしくお願いいたしますね！　心鈴先生！",
        "Name": "ルリヲ"
    },
    {
        "File": "fem_rur_10117",
        "Text": "お酒なんてわけわかんない事話してる場合じゃないって、そもそもあんなもんアルコール入ってればいいわけじゃん",
        "Name": "ルリヲ"
    },
    {
        "File": "fem_rur_10151",
        "Text": "な、なんか、怖い話をしているのかな？",
        "Name": "ルリヲ"
    },
    {
        "File": "fem_rur_10153",
        "Text": "そうなの？　マジ怖な感じなんですけど！！",
        "Name": "ルリヲ"
    },
    {
        "File": "fem_rur_10154",
        "Text": "マジマジですか！？　マジでルリヲ、そういう怖い系ヤバたんなヤツなんですけど！",
        "Name": "ルリヲ"
    },
    {
        "File": "fem_rur_10156",
        "Text": "そういえば、草薙ちゃん、この絵がどうこう言ってたね",
        "Name": "ルリヲ"
    },
    {
        "File": "fem_rur_10157",
        "Text": "げ？　これ贋作なの？　モネのレプリカか何かと思ってた",
        "Name": "ルリヲ"
    },
    {
        "File": "fem_rur_10158",
        "Text": "校長先生がこんな絵上手かったとかマジですか？",
        "Name": "ルリヲ"
    },
    {
        "File": "fem_rur_10160",
        "Text": "すごい芸術家って事ですよね",
        "Name": "ルリヲ"
    },
    {
        "File": "fem_rur_10161",
        "Text": "そうかな？　だって、あれだけの贋作だったら相手は相当なものだったのはバカな私でも分かるんじゃねぇかと",
        "Name": "ルリヲ"
    },
    {
        "File": "fem_rur_10162",
        "Text": "ん？　でも少しおかしくね？　校長先生って年齢いくつなんですか？",
        "Name": "ルリヲ"
    },
    {
        "File": "fem_rur_10163",
        "Text": "そんだとやっぱりおかしいじゃん？　この花瓶は静流さんの作品なんだよね",
        "Name": "ルリヲ"
    },
    {
        "File": "fem_rur_10165",
        "Text": "そしたら、この花瓶は、違う時期に作られた事になるっつー事になりますよねぇ",
        "Name": "ルリヲ"
    },
    {
        "File": "fem_rur_10166",
        "Text": "なんで、そんな時間差で作ったんですか？",
        "Name": "ルリヲ"
    },
    {
        "File": "fem_rur_10167",
        "Text": "静流さんが騙そうとした相手って、心鈴ちゃんのお母さんだったの？",
        "Name": "ルリヲ"
    },
    {
        "File": "fem_rur_10169",
        "Text": "うんうん。とりあえずスマイルでいかないかな？",
        "Name": "ルリヲ"
    },
    {
        "File": "fem_rur_10170",
        "Text": "百合かよ！",
        "Name": "ルリヲ"
    },
    {
        "File": "fem_rur_10171",
        "Text": "師弟愛かよ！　なんかいろいろ羨ましいなぁ。寧ちゃんは！",
        "Name": "ルリヲ"
    },
    {
        "File": "fem_rur_10172",
        "Text": "ん？　私ですか？",
        "Name": "ルリヲ"
    },
    {
        "File": "fem_rur_10078",
        "Text": "草薙ちゃんの謙遜は本当に嫌味だったんだけどさ！　寧ちゃんまでそんなこと言い出して！！　ルリヲには困惑しかないっつーの！",
        "Name": "ルリヲ"
    },
    {
        "File": "fem_rur_10080",
        "Text": "はっ！　その凄いルリヲちゃんは、何も賞を取れませんでしたけどね！！　どういう事ですか！？　マジで爆発しろよ世界！",
        "Name": "ルリヲ"
    },
    {
        "File": "fem_rur_10081",
        "Text": "あぁ！　今さらご忠告でございますかぁ？　はぁ？　だったら言えよ！",
        "Name": "ルリヲ"
    },
    {
        "File": "fem_rur_10082",
        "Text": "つーか背伸びもするに決まってるっつーの！　こんちきしょう",
        "Name": "ルリヲ"
    },
    {
        "File": "fem_rur_10083",
        "Text": "だいたいさぁ……なんか今回のFIRST展は寧ちゃんに草薙ちゃんはつきっきりだったしさぁ……もうひどいとしか言いようがなくねぇ？",
        "Name": "ルリヲ"
    },
    {
        "File": "fem_rur_10086",
        "Text": "う゛っ、前言撤回。寧ちゃん全然イヤなやつじゃないです。あんな賞を取って、ムーア公募展に推薦されたのに、まだ私なんかをライバルと言ってくれるのですから",
        "Name": "ルリヲ"
    },
    {
        "File": "fem_rur_10087",
        "Text": "う、うう……なんか、すごい人格者すぎて、ルリヲさんは引いてしまいます。あとカリスってなんですか？　横文字使われるとルリヲは良く分からないのですよ",
        "Name": "ルリヲ"
    },
    {
        "File": "fem_rur_10090",
        "Text": "うう……くやしい。その栄冠に輝くのは、このア・ロウアワーキウイちゃんだったハズなのにぃ……",
        "Name": "ルリヲ"
    },
    {
        "File": "fem_rur_10094",
        "Text": "こちら？　こちらって……",
        "Name": "ルリヲ"
    },
    {
        "File": "fem_rur_10095",
        "Text": "み、宮崎みすゞ先生？",
        "Name": "ルリヲ"
    },
    {
        "File": "fem_rur_10097",
        "Text": "わっ、宮崎みすゞ先生！　私のPNとか覚えてくださっているのですか！",
        "Name": "ルリヲ"
    },
    {
        "File": "fem_rur_10098",
        "Text": "草薙ちゃん！　私、宮崎みすゞに認知されているんだよ！　すごくね？　巨匠だよ。世界的な巨匠が目にかけているとか凄すぎだろ！",
        "Name": "ルリヲ"
    },
    {
        "File": "fem_rur_10099",
        "Text": "ルリヲのPNは変じゃねぇっつーの！",
        "Name": "ルリヲ"
    },
    {
        "File": "fem_rur_10100",
        "Text": "“生のキウイ時間”って意味ですよ。かわいさヤバたんスわ",
        "Name": "ルリヲ"
    },
    {
        "File": "fem_rur_10101",
        "Text": "氷川ルリヲなのです",
        "Name": "ルリヲ"
    },
    {
        "File": "fem_rur_10102",
        "Text": "あ、もしかして分かっちゃいましたか？",
        "Name": "ルリヲ"
    },
    {
        "File": "fem_rur_10103",
        "Text": "秘密だしー",
        "Name": "ルリヲ"
    },
    {
        "File": "fem_rur_10105",
        "Text": "おやおや、今さら気がついたんすかー？",
        "Name": "ルリヲ"
    },
    {
        "File": "fem_rur_10108",
        "Text": "ムキー！　そんな事ありませんよー！　英単語さえいろいろ知ってれば出来るものなんですよ！",
        "Name": "ルリヲ"
    },
    {
        "File": "fem_rur_10109",
        "Text": "ま、まぁ、少しはお姉ちゃんに手伝ってもらったといいますかー",
        "Name": "ルリヲ"
    },
    {
        "File": "fem_rur_10110",
        "Text": "ガイシケーつーところに勤めているぐらいですからなぁ",
        "Name": "ルリヲ"
    },
    {
        "File": "fem_rur_10113",
        "Text": "う゛……頼む前に断られた",
        "Name": "ルリヲ"
    },
    {
        "File": "fem_rur_10115",
        "Text": "和解完了って事で、さぁ、パーティを続けましょう！",
        "Name": "ルリヲ"
    },
    {
        "File": "fem_rur_10116",
        "Text": "今後よろしくお願いいたしますね！　心鈴先生！",
        "Name": "ルリヲ"
    },
    {
        "File": "fem_rur_10117",
        "Text": "お酒なんてわけわかんない事話してる場合じゃないって、そもそもあんなもんアルコール入ってればいいわけじゃん",
        "Name": "ルリヲ"
    },
    {
        "File": "fem_rur_10119",
        "Text": "わぁ、今日は心鈴先生がいるのですね！",
        "Name": "ルリヲ"
    },
    {
        "File": "fem_rur_10120",
        "Text": "寧ちゃんには悪いけど、ずっとつきっきりで宮崎みすゞ先生に教わっていたんだもん。今日は出し抜くしかない",
        "Name": "ルリヲ"
    },
    {
        "File": "fem_rur_10121",
        "Text": "そうですよ！　そろそろムーア展の〆切り間近ですから！",
        "Name": "ルリヲ"
    },
    {
        "File": "fem_rur_10122",
        "Text": "はい、FIRST展では寧ちゃんに後れを取りましたが、今度は負けません",
        "Name": "ルリヲ"
    },
    {
        "File": "fem_rur_10123",
        "Text": "はい！",
        "Name": "ルリヲ"
    },
    {
        "File": "fem_rur_10124",
        "Text": "こんな感じです！",
        "Name": "ルリヲ"
    },
    {
        "File": "fem_rur_10125",
        "Text": "あ、分かりますか？",
        "Name": "ルリヲ"
    },
    {
        "File": "fem_rur_10126",
        "Text": "私の師匠は！",
        "Name": "ルリヲ"
    },
    {
        "File": "fem_rur_10127",
        "Text": "氷川里奈なのです！",
        "Name": "ルリヲ"
    },
    {
        "File": "fem_rur_10128",
        "Text": "え？　そこまで分かっちゃいます？",
        "Name": "ルリヲ"
    },
    {
        "File": "fem_rur_10129",
        "Text": "それでも、お姉ちゃんは昔からずっと私に教えてくれますからねぇ",
        "Name": "ルリヲ"
    },
    {
        "File": "fem_rur_10130",
        "Text": "はい！",
        "Name": "ルリヲ"
    },
    {
        "File": "fem_rur_10131",
        "Text": "え？　つまり、お姉ちゃん以外から教わるなと？",
        "Name": "ルリヲ"
    },
    {
        "File": "fem_rur_10132",
        "Text": "で、でも……",
        "Name": "ルリヲ"
    },
    {
        "File": "fem_rur_10133",
        "Text": "うぉぉぉぉおおおお！　すげぇ、テンションマックスでしょ！",
        "Name": "ルリヲ"
    },
    {
        "File": "fem_rur_10134",
        "Text": "そうかー、だったら小声でテンションマックス状態表現するよー",
        "Name": "ルリヲ"
    },
    {
        "File": "fem_rur_10135",
        "Text": "そんなあらたまることもないっしょ、ねぇ草薙ちゃん",
        "Name": "ルリヲ"
    },
    {
        "File": "fem_rur_10136",
        "Text": "仲良くなんて当たり前じゃん！",
        "Name": "ルリヲ"
    },
    {
        "File": "fem_rur_10137",
        "Text": "目標が目の前にいるとやる気でるからねぇ",
        "Name": "ルリヲ"
    },
    {
        "File": "fem_rur_10140",
        "Text": "いやいや、実際、管理しているの草薙ちゃんじゃん",
        "Name": "ルリヲ"
    },
    {
        "File": "fem_rur_10141",
        "Text": "えへへ、見てくださいよ。なかなか面白いですよ",
        "Name": "ルリヲ"
    },
    {
        "File": "fem_rur_10142",
        "Text": "どうですか？　結構おもしろいでしょ？",
        "Name": "ルリヲ"
    },
    {
        "File": "fem_rur_10143",
        "Text": "やっぱりそこで止まりますか？　それだけ凄いでしょ？",
        "Name": "ルリヲ"
    },
    {
        "File": "fem_rur_10144",
        "Text": "え？",
        "Name": "ルリヲ"
    },
    {
        "File": "fem_rur_10145",
        "Text": "またコンペ予定です",
        "Name": "ルリヲ"
    },
    {
        "File": "fem_rur_10146",
        "Text": "いやいや、相手が誰であろうと負けないのがこのルリヲちゃんなのです",
        "Name": "ルリヲ"
    },
    {
        "File": "fem_rur_10147",
        "Text": "人の話を聞いてないんかい！",
        "Name": "ルリヲ"
    },
    {
        "File": "fem_rur_10148",
        "Text": "って！",
        "Name": "ルリヲ"
    },
    {
        "File": "fem_rur_10174",
        "Text": "前回の奨励賞は、あんまり誇れたものじゃなかったのですけど……",
        "Name": "ルリヲ"
    },
    {
        "File": "fem_rur_10175",
        "Text": "もう少し草薙ちゃんが教えてくれたらどうにかなったのかもだよ！",
        "Name": "ルリヲ"
    },
    {
        "File": "fem_rur_10176",
        "Text": "そうだよ",
        "Name": "ルリヲ"
    },
    {
        "File": "fem_rur_10177",
        "Text": "どうだろう。たしかにプロ顔負けの戦績ではあるのだけど……藝大受かるのもそれなりに大変だし",
        "Name": "ルリヲ"
    },
    {
        "File": "fem_rur_10178",
        "Text": "で、でもさぁ。やっぱりちゃんと藝大用の勉強とかしなきゃだし",
        "Name": "ルリヲ"
    },
    {
        "File": "fem_rur_10179",
        "Text": "夏目圭さんじゃあるまいしー。この年齢で簡単にとれないじゃん",
        "Name": "ルリヲ"
    },
    {
        "File": "fem_rur_10180",
        "Text": "でも、でもさ",
        "Name": "ルリヲ"
    },
    {
        "File": "fem_rur_10181",
        "Text": "……っ",
        "Name": "ルリヲ"
    },
    {
        "File": "fem_rur_10182",
        "Text": "でもさ……私が良くても、私の後だって、生徒は入ってくるわけだし……",
        "Name": "ルリヲ"
    },
    {
        "File": "fem_rur_10183",
        "Text": "けどさ！",
        "Name": "ルリヲ"
    },
    {
        "File": "fem_rur_10184",
        "Text": "……",
        "Name": "ルリヲ"
    },
    {
        "File": "fem_rur_10185",
        "Text": "……",
        "Name": "ルリヲ"
    },
    {
        "File": "fem_rur_10186",
        "Text": "咲崎さんもー、そんな校長いじめちゃダメですよー",
        "Name": "ルリヲ"
    },
    {
        "File": "fem_rur_10187",
        "Text": "チョリース先輩方お久しぶりっス",
        "Name": "ルリヲ"
    },
    {
        "File": "fem_rur_10189",
        "Text": "そんなこんなで私の顔を立ててですねぇ",
        "Name": "ルリヲ"
    }
]